[{"town": "Bloomfield", "url": "http://rocwiki.org/Sharks_Ice_Cream", "name": "Sharks Ice Cream"}, {"town": "Brighton", "url": "http://rocwiki.org/AVVINO", "name": "AVVINO"}, {"town": "Brighton", "url": "http://rocwiki.org/Agave_Mexican_Grill", "name": "Agave Mexican Grill"}, {"town": "Brighton", "url": "http://rocwiki.org/Aja_Noodle_Company", "name": "Aja Noodle Company"}, {"town": "Brighton", "url": "http://rocwiki.org/Amaya_Bar_and_Grill", "name": "Amaya Bar and Grill"}, {"town": "Brighton", "url": "http://rocwiki.org/Arby%27s", "name": "Arby's"}, {"town": "Brighton", "url": "http://rocwiki.org/Bamboo_House", "name": "Bamboo House"}, {"town": "Brighton", "url": "http://rocwiki.org/Brandani%27s", "name": "Brandani's"}, {"town": "Brighton", "url": "http://rocwiki.org/Brick_Wood_Fired_Pizza_%26_Pasta", "name": "Brick Wood Fired Pizza & Pasta"}, {"town": "Brighton", "url": "http://rocwiki.org/Cerame%27s_Italian_Villa", "name": "Cerame's Italian Villa"}, {"town": "Brighton", "url": "http://rocwiki.org/Char_Broil_Family_Restaurant", "name": "Char Broil Family Restaurant"}, {"town": "Brighton", "url": "http://rocwiki.org/Chen_Garden", "name": "Chen Garden"}, {"town": "Brighton", "url": "http://rocwiki.org/Chopstix_Chinese_Restaurant", "name": "Chopstix Chinese Restaurant"}, {"town": "Brighton", "url": "http://rocwiki.org/Crab_Shack", "name": "Crab Shack"}, {"town": "Brighton", "url": "http://rocwiki.org/Delmonicos_Italian_Steakhouse", "name": "Delmonicos Italian Steakhouse"}, {"town": "Brighton", "url": "http://rocwiki.org/DiBella%27s", "name": "DiBella's"}, {"town": "Brighton", "url": "http://rocwiki.org/Don%27s_Original", "name": "Don's Original"}, {"town": "Brighton", "url": "http://rocwiki.org/Dunkin%27_Donuts", "name": "Dunkin' Donuts"}, {"town": "Brighton", "url": "http://rocwiki.org/Flour_City_Grill", "name": "Flour City Grill"}, {"town": "Brighton", "url": "http://rocwiki.org/Fox%27s", "name": "Fox's"}, {"town": "Brighton", "url": "http://rocwiki.org/Friendly%27s", "name": "Friendly's"}, {"town": "Brighton", "url": "http://rocwiki.org/Geulah%27s_Kosher_Cafe", "name": "Geulah's Kosher Cafe"}, {"town": "Brighton", "url": "http://rocwiki.org/Golden_Dynasty", "name": "Golden Dynasty"}, {"town": "Brighton", "url": "http://rocwiki.org/Great_Harvest_Bread_Company", "name": "Great Harvest Bread Company"}, {"town": "Brighton", "url": "http://rocwiki.org/Great_Northern_Pizza_Kitchens", "name": "Great Northern Pizza Kitchens"}, {"town": "Brighton", "url": "http://rocwiki.org/Grinnell%27s_Restaurant", "name": "Grinnell's Restaurant"}, {"town": "Brighton", "url": "http://rocwiki.org/Halfmoon_Creative_Salads", "name": "Halfmoon Creative Salads"}, {"town": "Brighton", "url": "http://rocwiki.org/Jay%27s_Diner", "name": "Jay's Diner"}, {"town": "Brighton", "url": "http://rocwiki.org/Ken%27s_Pizza_Corner", "name": "Ken's Pizza Corner"}, {"town": "Brighton", "url": "http://rocwiki.org/Leo%27s_Deli", "name": "Leo's Deli"}, {"town": "Brighton", "url": "http://rocwiki.org/Mamasan%27s", "name": "Mamasan's"}, {"town": "Brighton", "url": "http://rocwiki.org/Mario%27s_Italian_Steakhouse_%26_Catering", "name": "Mario's Italian Steakhouse & Catering"}, {"town": "Brighton", "url": "http://rocwiki.org/Max_Chophouse", "name": "Max Chophouse"}, {"town": "Brighton", "url": "http://rocwiki.org/Michelina%27s_Italian_Eatery", "name": "Michelina's Italian Eatery"}, {"town": "Brighton", "url": "http://rocwiki.org/New_Cantonese", "name": "New Cantonese"}, {"town": "Brighton", "url": "http://rocwiki.org/Oakleaf_Eatery", "name": "Oakleaf Eatery"}, {"town": "Brighton", "url": "http://rocwiki.org/The_Otter_Lodge", "name": "The Otter Lodge"}, {"town": "Brighton", "url": "http://rocwiki.org/Panera_Bread", "name": "Panera Bread"}, {"town": "Brighton", "url": "http://rocwiki.org/Phillips_European_Restaurant", "name": "Phillips European Restaurant"}, {"town": "Brighton", "url": "http://rocwiki.org/Pizza_Hut", "name": "Pizza Hut"}, {"town": "Brighton", "url": "http://rocwiki.org/Sai_Gon_Restaurant", "name": "Sai Gon Restaurant"}, {"town": "Brighton", "url": "http://rocwiki.org/Sakura_Home", "name": "Sakura Home"}, {"town": "Brighton", "url": "http://rocwiki.org/Salvatore%27s_Old_Fashioned_Pizzeria", "name": "Salvatore's Old Fashioned Pizzeria"}, {"town": "Brighton", "url": "http://rocwiki.org/Clover_Lanes", "name": "Clover Lanes"}, {"town": "Brighton", "url": "http://rocwiki.org/Schallers", "name": "Schallers"}, {"town": "Brighton", "url": "http://rocwiki.org/Seoul_House", "name": "Seoul House"}, {"town": "Brighton", "url": "http://rocwiki.org/Subway_Restaurants", "name": "Subway Restaurants"}, {"town": "Brighton", "url": "http://rocwiki.org/TGI_Friday%27s", "name": "TGI Friday's"}, {"town": "Brighton", "url": "http://rocwiki.org/Yummy_Garden", "name": "Yummy Garden"}, {"town": "Brighton", "url": "http://rocwiki.org/Zebb%27s_Deluxe_Grill_%26_Bar", "name": "Zebb's Deluxe Grill & Bar"}, {"town": "City of Rochester", "url": "http://rocwiki.org/Arnett_Cafe", "name": "Arnett Cafe"}, {"town": "City of Rochester", "url": "http://rocwiki.org/Boulder_Coffee_Co.", "name": "Boulder Coffee Co."}, {"town": "City of Rochester", "url": "http://rocwiki.org/Brooks_Landing_Diner", "name": "Brooks Landing Diner"}, {"town": "City of Rochester", "url": "http://rocwiki.org/Campi%27s", "name": "Campi's"}, {"town": "City of Rochester", "url": "http://rocwiki.org/Capital_Subs", "name": "Capital Subs"}, {"town": "City of Rochester", "url": "http://rocwiki.org/Chili_Diner", "name": "Chili Diner"}, {"town": "City of Rochester", "url": "http://rocwiki.org/El_Latino_Restaurant", "name": "El Latino Restaurant"}, {"town": "City of Rochester", "url": "http://rocwiki.org/Holley%27s_Cafe_and_Catering", "name": "Holley's Cafe and Catering"}, {"town": "City of Rochester", "url": "http://rocwiki.org/LJ%27s", "name": "LJ's"}, {"town": "City of Rochester", "url": "http://rocwiki.org/LOM2FWA", "name": "LOM2FWA"}, {"town": "City of Rochester", "url": "http://rocwiki.org/Livie%27s_Jamaican_Restaurant_and_Import_Market", "name": "Livie's Jamaican Restaurant and Import Market"}, {"town": "City of Rochester", "url": "http://rocwiki.org/Menezes_Pizza", "name": "Menezes Pizza"}, {"town": "City of Rochester", "url": "http://rocwiki.org/Natural_Vibes", "name": "Natural Vibes"}, {"town": "City of Rochester", "url": "http://rocwiki.org/Obsessions_Bar_and_Grill", "name": "Obsessions Bar and Grill"}, {"town": "City of Rochester", "url": "http://rocwiki.org/People%27s_Choice_Kitchen", "name": "People's Choice Kitchen"}, {"town": "City of Rochester", "url": "http://rocwiki.org/Sonny%27s_Side_Family_Kitchen", "name": "Sonny's Side Family Kitchen"}, {"town": "City of Rochester", "url": "http://rocwiki.org/Subway_Restaurants", "name": "Subway"}, {"town": "City of Rochester", "url": "http://rocwiki.org/Unkl_Moe%27s", "name": "Unkl Moe's"}, {"town": "City of Rochester", "url": "http://rocwiki.org/Whatta-Cuisine_Vietnamese_Restaurant", "name": "Whatta-Cuisine Vietnamese Restaurant"}, {"town": "City of Rochester", "url": "http://rocwiki.org/Chang_Lung_Restaurant", "name": "Chang Lung Restaurant"}, {"town": "City of Rochester", "url": "http://rocwiki.org/Golden_Fox_Restaurant", "name": "Golden Fox Restaurant"}, {"town": "City of Rochester", "url": "http://rocwiki.org/Goodman%27s_New_York_Style_Pizzeria", "name": "Goodman's New York Style Pizzeria"}, {"town": "City of Rochester", "url": "http://rocwiki.org/Grandma%27s_Kitchen", "name": "Grandma's Kitchen"}, {"town": "City of Rochester", "url": "http://rocwiki.org/Lorraine%27s_Food_Factory", "name": "Lorraine's Food Factory"}, {"town": "City of Rochester", "url": "http://rocwiki.org/McDonald%27s", "name": "McDonald's"}, {"town": "City of Rochester", "url": "http://rocwiki.org/Natural_Vibes", "name": "Natural Vibes Jerk Hut 2"}, {"town": "City of Rochester", "url": "http://rocwiki.org/Sticky_Lips_Pit_BBQ", "name": "Sticky Lips Pit BBQ"}, {"town": "City of Rochester", "url": "http://rocwiki.org/Swan_Market", "name": "Swan Market"}, {"town": "City of Rochester", "url": "http://rocwiki.org/DiPisa_Old_World_Submarines", "name": "DiPisa Old World Submarines"}, {"town": "City of Rochester", "url": "http://rocwiki.org/Flat_Iron_Cafe", "name": "Flat Iron Cafe"}, {"town": "City of Rochester", "url": "http://rocwiki.org/Rocky%27s", "name": "Rocky's"}, {"town": "City of Rochester", "url": "http://rocwiki.org/Roncone%27s", "name": "Roncone's"}, {"town": "City of Rochester", "url": "http://rocwiki.org/Abbott%27s_Frozen_Custard", "name": "Abbott's Frozen Custard"}, {"town": "City of Rochester", "url": "http://rocwiki.org/California_Rollin%27", "name": "California Rollin'"}, {"town": "City of Rochester", "url": "http://rocwiki.org/Cheeburger_Cheeburger", "name": "Cheeburger Cheeburger"}, {"town": "City of Rochester", "url": "http://rocwiki.org/Harbor_Hots", "name": "Harbor Hots"}, {"town": "City of Rochester", "url": "http://rocwiki.org/Hose_22_Firehouse_Grill", "name": "Hose 22 Firehouse Grill"}, {"town": "City of Rochester", "url": "http://rocwiki.org/LDR_Char_Pit", "name": "LDR Char Pit"}, {"town": "City of Rochester", "url": "http://rocwiki.org/Lake_Chinese_Food", "name": "Lake Chinese Food"}, {"town": "City of Rochester", "url": "http://rocwiki.org/Lakesiders_Sports_Bar_%26_Grill", "name": "Lakesiders Sports Bar & Grill"}, {"town": "City of Rochester", "url": "http://rocwiki.org/Mama%27s_Pizza_Kitchen", "name": "Mama's Pizza Kitchen"}, {"town": "City of Rochester", "url": "http://rocwiki.org/Mr._Dominic%27s", "name": "Mr. Dominic's"}, {"town": "City of Rochester", "url": "http://rocwiki.org/Nola%27s_BBQ", "name": "Nola's BBQ"}, {"town": "City of Rochester", "url": "http://rocwiki.org/Nutty_Bavarian", "name": "Nutty Bavarian"}, {"town": "City of Rochester", "url": "http://rocwiki.org/Pelican%27s_Nest_Restaurant", "name": "Pelican's Nest Restaurant"}, {"town": "City of Rochester", "url": "http://rocwiki.org/Rab%27s_Woodshed", "name": "Rab's Woodshed"}, {"town": "City of Rochester", "url": "http://rocwiki.org/Scuttlebutts", "name": "Scuttlebutts"}, {"town": "City of Rochester", "url": "http://rocwiki.org/Steel_River_BBQ_Bar_%26_Grill", "name": "Steel River BBQ Bar & Grill"}, {"town": "City of Rochester", "url": "http://rocwiki.org/Windjammers_Bar_%26_Grill", "name": "Windjammers Bar & Grill"}, {"town": "City of Rochester", "url": "http://rocwiki.org/Harvest_Cafe", "name": "Harvest Cafe"}, {"town": "City of Rochester", "url": "http://rocwiki.org/Nathaniel%27s", "name": "Nathaniel's"}, {"town": "City of Rochester", "url": "http://rocwiki.org/Panzari%27s_Italian_Bistro", "name": "Panzari's Italian Bistro"}, {"town": "City of Rochester", "url": "http://rocwiki.org/Subway_Restaurants", "name": "Subway"}, {"town": "City of Rochester", "url": "http://rocwiki.org/Ticas_With_A_Twist", "name": "Ticas With A Twist"}, {"town": "City of Rochester", "url": "http://rocwiki.org/Tony_D%27s_Coal_Fired_Pizza", "name": "Tony D's Coal Fired Pizza"}, {"town": "City of Rochester", "url": "http://rocwiki.org/Downtown_Restaurants", "name": "Downtown Restaurants"}, {"town": "City of Rochester", "url": "http://rocwiki.org/Amore_Italian_Restaurant_%26_Wine_Bar", "name": "Amore Italian Restaurant & Wine Bar"}, {"town": "City of Rochester", "url": "http://rocwiki.org/The_Brighton", "name": "The Brighton on East"}, {"town": "City of Rochester", "url": "http://rocwiki.org/CanalTown_Coffee_Roasters", "name": "CanalTown Coffee Roasters"}, {"town": "City of Rochester", "url": "http://rocwiki.org/Char_Steak_%26_Lounge", "name": "Char Steak & Lounge"}, {"town": "City of Rochester", "url": "http://rocwiki.org/Country_Club_Diner", "name": "Country Club Diner"}, {"town": "City of Rochester", "url": "http://rocwiki.org/DiBella%27s", "name": "DiBella's"}, {"town": "City of Rochester", "url": "http://rocwiki.org/Dunkin%27_Donuts", "name": "Dunkin' Donuts"}, {"town": "City of Rochester", "url": "http://rocwiki.org/Flour_City_Grill", "name": "Flour City Grill"}, {"town": "City of Rochester", "url": "http://rocwiki.org/Joe_Bean", "name": "Joe Bean"}, {"town": "City of Rochester", "url": "http://rocwiki.org/McDonald%27s", "name": "McDonald's"}, {"town": "City of Rochester", "url": "http://rocwiki.org/New_Wong%27s_Kitchen", "name": "New Wong's Kitchen"}, {"town": "City of Rochester", "url": "http://rocwiki.org/Pomodoro_Grill_and_Wine_Bar", "name": "Pomodoro Grill and Wine Bar"}, {"town": "City of Rochester", "url": "http://rocwiki.org/Real_Life_Food_and_Fitness", "name": "Real Life Food and Fitness"}, {"town": "City of Rochester", "url": "http://rocwiki.org/The_Revelry", "name": "The Revelry"}, {"town": "City of Rochester", "url": "http://rocwiki.org/Ristorante_Lucano", "name": "Ristorante Lucano"}, {"town": "City of Rochester", "url": "http://rocwiki.org/Subway_Restaurants", "name": "Subway"}, {"town": "City of Rochester", "url": "http://rocwiki.org/Tim_Hortons", "name": "Tim Hortons"}, {"town": "City of Rochester", "url": "http://rocwiki.org/Wendy%27s", "name": "Wendy's"}, {"town": "City of Rochester", "url": "http://rocwiki.org/2_Vine", "name": "2 Vine"}, {"town": "City of Rochester", "url": "http://rocwiki.org/Aunt_Rosie%27s", "name": "Aunt Rosie's"}, {"town": "City of Rochester", "url": "http://rocwiki.org/Bamba_Bistro", "name": "Bamba Bistro"}, {"town": "City of Rochester", "url": "http://rocwiki.org/Cam%27s_Pizzeria", "name": "Cam's Pizzeria"}, {"town": "City of Rochester", "url": "http://rocwiki.org/Captain%27s_Attic_Restaurant_%26_Bar", "name": "Captain's Attic Restaurant & Bar"}, {"town": "City of Rochester", "url": "http://rocwiki.org/Chestnut_Cafe", "name": "Chestnut Cafe"}, {"town": "City of Rochester", "url": "http://rocwiki.org/Everything_Iz_Good", "name": "Everything Iz Good"}, {"town": "City of Rochester", "url": "http://rocwiki.org/Fra%C3%AEche_Bistro_and_Dessert_Bar", "name": "Fra\u00eeche Bistro and Dessert Bar"}, {"town": "City of Rochester", "url": "http://rocwiki.org/Golden_Port", "name": "Golden Port"}, {"town": "City of Rochester", "url": "http://rocwiki.org/The_Grill_at_One", "name": "The Grill at One"}, {"town": "City of Rochester", "url": "http://rocwiki.org/Havana_Cabana", "name": "Havana Cabana"}, {"town": "City of Rochester", "url": "http://rocwiki.org/House_of_Sushi", "name": "House of Sushi"}, {"town": "City of Rochester", "url": "http://rocwiki.org/Jim%27s_Restaurant_Too", "name": "Jim's Restaurant Too"}, {"town": "City of Rochester", "url": "http://rocwiki.org/Little_Cafe", "name": "Little Cafe"}, {"town": "City of Rochester", "url": "http://rocwiki.org/Ludwig%27s_Center_Stage_Cafe", "name": "Ludwig's Center Stage Cafe"}, {"town": "City of Rochester", "url": "http://rocwiki.org/Max_of_Eastman_Place", "name": "Max of Eastman Place"}, {"town": "City of Rochester", "url": "http://rocwiki.org/Mitch%27s_Restaurant", "name": "Mitch's Restaurant"}, {"town": "City of Rochester", "url": "http://rocwiki.org/Orange_Glory_Cafe", "name": "Orange Glory Cafe"}, {"town": "City of Rochester", "url": "http://rocwiki.org/The_Pita_Pit", "name": "The Pita Pit"}, {"town": "City of Rochester", "url": "http://rocwiki.org/Pontillo%27s", "name": "Pontillo's Pizza"}, {"town": "City of Rochester", "url": "http://rocwiki.org/Shema_Sushi", "name": "Shema Sushi"}, {"town": "City of Rochester", "url": "http://rocwiki.org/Shui_Asian_Fusion", "name": "Shui Asian Fusion"}, {"town": "City of Rochester", "url": "http://rocwiki.org/Stromboli_Express", "name": "Stromboli Express"}, {"town": "City of Rochester", "url": "http://rocwiki.org/Subway_Restaurants", "name": "Subway"}, {"town": "City of Rochester", "url": "http://rocwiki.org/Tequila_Loco", "name": "Tequila Loco"}, {"town": "City of Rochester", "url": "http://rocwiki.org/Tournedo%27s_Restaurant", "name": "Tournedo's Restaurant"}, {"town": "City of Rochester", "url": "http://rocwiki.org/Veneto", "name": "Veneto"}, {"town": "City of Rochester", "url": "http://rocwiki.org/Victoire", "name": "Victoire"}, {"town": "City of Rochester", "url": "http://rocwiki.org/CJ%27s_Southern_Soul_Restaurant", "name": "CJ's Southern Soul Restaurant"}, {"town": "City of Rochester", "url": "http://rocwiki.org/Domino%27s_Pizza", "name": "Domino's Pizza"}, {"town": "City of Rochester", "url": "http://rocwiki.org/Dunkin%27_Donuts", "name": "Dunkin' Donuts"}, {"town": "City of Rochester", "url": "http://rocwiki.org/El_Jibarito_Restaurant", "name": "El Jibarito"}, {"town": "City of Rochester", "url": "http://rocwiki.org/El_Taino", "name": "El Taino"}, {"town": "City of Rochester", "url": "http://rocwiki.org/Flat_Iron_Cafe", "name": "Flat Iron Cafe"}, {"town": "City of Rochester", "url": "http://rocwiki.org/Lake_Avenue_Hots", "name": "Lake Avenue Hots"}, {"town": "City of Rochester", "url": "http://rocwiki.org/Mark%27s_Texas_Hots", "name": "Mark's Texas Hots"}, {"town": "City of Rochester", "url": "http://rocwiki.org/Marvin_Mozzeroni%27s", "name": "Marvin Mozzeroni's"}, {"town": "City of Rochester", "url": "http://rocwiki.org/McDonald%27s", "name": "McDonald's"}, {"town": "City of Rochester", "url": "http://rocwiki.org/Popeyes_Chicken_%26_Biscuits", "name": "Popeyes Chicken & Biscuits"}, {"town": "City of Rochester", "url": "http://rocwiki.org/Tim_Hortons", "name": "Tim Hortons"}, {"town": "City of Rochester", "url": "http://rocwiki.org/Wendy%27s", "name": "Wendy's"}, {"town": "City of Rochester", "url": "http://rocwiki.org/Glady%27s_Place", "name": "Glady's Place"}, {"town": "City of Rochester", "url": "http://rocwiki.org/Jerkers_Original_Take_Out", "name": "Jerkers Original Take Out"}, {"town": "City of Rochester", "url": "http://rocwiki.org/Mojoe%27s_Pizza", "name": "Mojoe's Pizza"}, {"town": "City of Rochester", "url": "http://rocwiki.org/Pop_Style_International", "name": "Pop Style International"}, {"town": "City of Rochester", "url": "http://rocwiki.org/This_Is_It", "name": "This Is It"}, {"town": "City of Rochester", "url": "http://rocwiki.org/Dunkin%27_Donuts", "name": "Dunkin' Donuts"}, {"town": "City of Rochester", "url": "http://rocwiki.org/East_Ridge_Hots", "name": "East Ridge Hots"}, {"town": "City of Rochester", "url": "http://rocwiki.org/El_Pilon_Criollo_Restaurant", "name": "El Pilon Criollo Restaurant"}, {"town": "City of Rochester", "url": "http://rocwiki.org/El_Sabor_de_la_Isla", "name": "El Sabor de la Isla"}, {"town": "City of Rochester", "url": "http://rocwiki.org/Halal_Market_and_Meats_Cafe", "name": "Halal Market and Meats Cafe"}, {"town": "City of Rochester", "url": "http://rocwiki.org/Kithno%27s_Seafood", "name": "Kithno's Seafood"}, {"town": "City of Rochester", "url": "http://rocwiki.org/Pudgie%27s_Pizza", "name": "Pudgie's Pizza"}, {"town": "City of Rochester", "url": "http://rocwiki.org/Sal%27s_Birdland", "name": "Sal's Birdland"}, {"town": "City of Rochester", "url": "http://rocwiki.org/Salvatore%27s_Old_Fashioned_Pizzeria", "name": "Salvatore's Old Fashioned Pizzeria"}, {"town": "City of Rochester", "url": "http://rocwiki.org/Crossroads_Coffeehouse", "name": "Crossroads Coffeehouse"}, {"town": "City of Rochester", "url": "http://rocwiki.org/Flavors_of_Asia", "name": "Flavors of Asia"}, {"town": "City of Rochester", "url": "http://rocwiki.org/Georgie%27s_Bakery", "name": "Georgie's Bakery"}, {"town": "City of Rochester", "url": "http://rocwiki.org/Highland_Park_Diner", "name": "Highland Park Diner"}, {"town": "City of Rochester", "url": "http://rocwiki.org/India_House", "name": "India House"}, {"town": "City of Rochester", "url": "http://rocwiki.org/Ming%27s_Noodles", "name": "Ming's Noodles"}, {"town": "City of Rochester", "url": "http://rocwiki.org/Rooney%27s", "name": "Rooney's"}, {"town": "City of Rochester", "url": "http://rocwiki.org/Salvatore%27s_Old_Fashioned_Pizzeria", "name": "Salvatore's Old Fashioned Pizzeria"}, {"town": "City of Rochester", "url": "http://rocwiki.org/Shiki", "name": "Shiki"}, {"town": "City of Rochester", "url": "http://rocwiki.org/South_Wedge_Diner", "name": "South Wedge Diner"}, {"town": "City of Rochester", "url": "http://rocwiki.org/Vinh-Hao_Music_%26_Video_and_Banh_Mi_Cafe", "name": "Vinh-Hao Music & Video and Banh Mi Cafe"}, {"town": "City of Rochester", "url": "http://rocwiki.org/White_Swans_Asia_Caffe", "name": "White Swans Asia Caffe"}, {"town": "City of Rochester", "url": "http://rocwiki.org/Zemeta_Ethiopian_Restaurant", "name": "Zemeta Ethiopian Restaurant"}, {"town": "City of Rochester", "url": "http://rocwiki.org/Ray_Ray%27s_Bar_%26_Grill", "name": "Ray Ray's Bar & Grill"}, {"town": "City of Rochester", "url": "http://rocwiki.org/Cam%27s_Pizzeria", "name": "Cam's Pizzeria"}, {"town": "City of Rochester", "url": "http://rocwiki.org/The_Distillery", "name": "The Distillery"}, {"town": "City of Rochester", "url": "http://rocwiki.org/Elmwood_Inn", "name": "Elmwood Inn"}, {"town": "City of Rochester", "url": "http://rocwiki.org/Pellegrino%27s_Deli_Cafe", "name": "Pellegrino's Deli Cafe"}, {"town": "City of Rochester", "url": "http://rocwiki.org/Tim_Hortons", "name": "Tim Hortons"}, {"town": "City of Rochester", "url": "http://rocwiki.org/Burger_King", "name": "Burger King"}, {"town": "City of Rochester", "url": "http://rocwiki.org/DiGiacco%E2%80%99s_Pizzeria", "name": "DiGiacco\u2019s Pizzeria"}, {"town": "City of Rochester", "url": "http://rocwiki.org/Dunkin%27_Donuts", "name": "Dunkin' Donuts"}, {"town": "City of Rochester", "url": "http://rocwiki.org/Lacagnina%27s_Italian_Deli", "name": "Lacagnina's Italian Deli"}, {"town": "City of Rochester", "url": "http://rocwiki.org/McDonald%27s", "name": "McDonald's"}, {"town": "City of Rochester", "url": "http://rocwiki.org/Parma_Johnny%27s_Italian_Grill", "name": "Parma Johnny's Italian Grill"}, {"town": "City of Rochester", "url": "http://rocwiki.org/Pho_Duong_Dong", "name": "Pho Duong Dong"}, {"town": "City of Rochester", "url": "http://rocwiki.org/Super_Wing_Chinese", "name": "Super Wing Chinese"}, {"town": "City of Rochester", "url": "http://rocwiki.org/Tim_Hortons", "name": "Tim Hortons"}, {"town": "City of Rochester", "url": "http://rocwiki.org/Barnard_Crossings_Bar_and_Grill", "name": "Barnard Crossings Bar and Grill"}, {"town": "City of Rochester", "url": "http://rocwiki.org/Bathtub_Billy%27s", "name": "Bathtub Billy's"}, {"town": "City of Rochester", "url": "http://rocwiki.org/California_Brew_Haus", "name": "California Brew Haus"}, {"town": "City of Rochester", "url": "http://rocwiki.org/Checker_Flag_Pizza", "name": "Checker Flag Pizza"}, {"town": "City of Rochester", "url": "http://rocwiki.org/Chinese_Hometown_Restaurant", "name": "Chinese Hometown Restaurant"}, {"town": "City of Rochester", "url": "http://rocwiki.org/Code_7_Burgers_%26_Beans", "name": "Code 7 Burgers & Beans"}, {"town": "City of Rochester", "url": "http://rocwiki.org/El_Coqui_Restaurant", "name": "El Coqui Restaurant"}, {"town": "City of Rochester", "url": "http://rocwiki.org/El%27s_Delicatessen", "name": "El's Delicatessen"}, {"town": "City of Rochester", "url": "http://rocwiki.org/H_%26_A_Deli", "name": "H & A Deli"}, {"town": "City of Rochester", "url": "http://rocwiki.org/Maplewood_Cafe", "name": "Maplewood Cafe"}, {"town": "City of Rochester", "url": "http://rocwiki.org/McGinnity%27s_Restaurant_%26_Party_House", "name": "McGinnity's Restaurant & Party House"}, {"town": "City of Rochester", "url": "http://rocwiki.org/Patti%27s_Pantry", "name": "Patti's Pantry"}, {"town": "City of Rochester", "url": "http://rocwiki.org/Peppermill_Restaurant", "name": "Peppermill Restaurant"}, {"town": "City of Rochester", "url": "http://rocwiki.org/Pizza_Hut", "name": "Pizza Hut"}, {"town": "City of Rochester", "url": "http://rocwiki.org/Ralf%27s_European_Meats_and_Delicatessen", "name": "Ralf's European Meats and Delicatessen"}, {"town": "City of Rochester", "url": "http://rocwiki.org/Rincon_Criollo", "name": "Rincon Criollo"}, {"town": "City of Rochester", "url": "http://rocwiki.org/Salvatore%27s_Old_Fashioned_Pizzeria", "name": "Salvatore's Old Fashioned Pizzeria"}, {"town": "City of Rochester", "url": "http://rocwiki.org/Subway_Restaurants", "name": "Subway"}, {"town": "City of Rochester", "url": "http://rocwiki.org/Taco_Bell", "name": "Taco Bell"}, {"town": "City of Rochester", "url": "http://rocwiki.org/Taste_Delicious", "name": "Taste Delicious"}, {"town": "City of Rochester", "url": "http://rocwiki.org/Tim_Hortons", "name": "Tim Hortons"}, {"town": "City of Rochester", "url": "http://rocwiki.org/Unlimited_Seafood", "name": "Unlimited Seafood"}, {"town": "City of Rochester", "url": "http://rocwiki.org/Welker%27s_Grill", "name": "Welker's Grill"}, {"town": "City of Rochester", "url": "http://rocwiki.org/West_Winds_Cafe", "name": "West Winds Cafe"}, {"town": "City of Rochester", "url": "http://rocwiki.org/Yummy_House", "name": "Yummy House"}, {"town": "City of Rochester", "url": "http://rocwiki.org/Market_District", "name": "Market District"}, {"town": "City of Rochester", "url": "http://rocwiki.org/Aladdin%27s_Natural_Eatery", "name": "Aladdin's Natural Eatery"}, {"town": "City of Rochester", "url": "http://rocwiki.org/Arby%27s", "name": "Arby's"}, {"town": "City of Rochester", "url": "http://rocwiki.org/Astoria", "name": "Astoria"}, {"town": "City of Rochester", "url": "http://rocwiki.org/The_Avenue_Diner", "name": "The Avenue Diner"}, {"town": "City of Rochester", "url": "http://rocwiki.org/Avenue_Eatery", "name": "Avenue Eatery"}, {"town": "City of Rochester", "url": "http://rocwiki.org/Big_Deal_Pizzeria", "name": "Big Deal Pizzeria"}, {"town": "City of Rochester", "url": "http://rocwiki.org/Brickwood_Grill", "name": "Brickwood Grill"}, {"town": "City of Rochester", "url": "http://rocwiki.org/Bruegger%27s", "name": "Bruegger's"}, {"town": "City of Rochester", "url": "http://rocwiki.org/Dac_Hoa", "name": "Dac Hoa"}, {"town": "City of Rochester", "url": "http://rocwiki.org/Dogtown_Hots", "name": "Dogtown Hots"}, {"town": "City of Rochester", "url": "http://rocwiki.org/Domino%27s_Pizza", "name": "Domino's Pizza"}, {"town": "City of Rochester", "url": "http://rocwiki.org/Dunkin%27_Donuts", "name": "Dunkin' Donuts"}, {"town": "City of Rochester", "url": "http://rocwiki.org/Jimmy_John%27s_Gourmet_Sandwiches", "name": "Jimmy John's"}, {"town": "City of Rochester", "url": "http://rocwiki.org/Han_Noodle_Bar", "name": "Han Noodle Bar"}, {"town": "City of Rochester", "url": "http://rocwiki.org/Little_Caesars_Pizza", "name": "Little Caesars Pizza"}, {"town": "City of Rochester", "url": "http://rocwiki.org/Mark%27s_Pizzeria", "name": "Mark's Pizzeria"}, {"town": "City of Rochester", "url": "http://rocwiki.org/Mark%27s_Texas_Hots", "name": "Mark's Texas Hots"}, {"town": "City of Rochester", "url": "http://rocwiki.org/McDonald%27s", "name": "McDonald's"}, {"town": "City of Rochester", "url": "http://rocwiki.org/Natural_Oasis_Cafe", "name": "Natural Oasis Cafe"}, {"town": "City of Rochester", "url": "http://rocwiki.org/Pho_Viet_Asian_Noodle_Bar", "name": "Pho Viet Asian Noodle Bar"}, {"town": "City of Rochester", "url": "http://rocwiki.org/Pizza_Hut", "name": "Pizza Hut"}, {"town": "City of Rochester", "url": "http://rocwiki.org/Plum_House", "name": "Plum House"}, {"town": "City of Rochester", "url": "http://rocwiki.org/Rocco", "name": "Rocco"}, {"town": "City of Rochester", "url": "http://rocwiki.org/SEA_Restaurant", "name": "SEA Restaurant"}, {"town": "City of Rochester", "url": "http://rocwiki.org/Sol_Burrito", "name": "Sol Burrito"}, {"town": "City of Rochester", "url": "http://rocwiki.org/South_Wedge_Hots_%26_Subs", "name": "South Wedge Hots & Subs"}, {"town": "City of Rochester", "url": "http://rocwiki.org/Starbucks", "name": "Starbucks"}, {"town": "City of Rochester", "url": "http://rocwiki.org/Subway_Restaurants", "name": "Subway"}, {"town": "City of Rochester", "url": "http://rocwiki.org/Texas_Blues_BBQ", "name": "Texas Blues BBQ"}, {"town": "City of Rochester", "url": "http://rocwiki.org/Voula%27s_Greek_Sweets", "name": "Voula's Greek Sweets"}, {"town": "City of Rochester", "url": "http://rocwiki.org/California_Rollin%27", "name": "California Rollin'"}, {"town": "City of Rochester", "url": "http://rocwiki.org/Chocolate_and_Vines", "name": "Chocolate and Vines"}, {"town": "City of Rochester", "url": "http://rocwiki.org/Dark_Horse_Coffee", "name": "Dark Horse Coffee"}, {"town": "City of Rochester", "url": "http://rocwiki.org/Edible%27s", "name": "Edible's"}, {"town": "City of Rochester", "url": "http://rocwiki.org/Espada_Brazilian_Steak", "name": "Espada Brazilian Steak"}, {"town": "City of Rochester", "url": "http://rocwiki.org/Gate_House_Cafe", "name": "Gate House Cafe"}, {"town": "City of Rochester", "url": "http://rocwiki.org/Good_Luck", "name": "Good Luck"}, {"town": "City of Rochester", "url": "http://rocwiki.org/Hot_Shots", "name": "Hot Shots"}, {"town": "City of Rochester", "url": "http://rocwiki.org/Lento", "name": "Lento"}, {"town": "City of Rochester", "url": "http://rocwiki.org/Salena%27s_Mexican_Restaurant", "name": "Salena's Mexican Restaurant"}, {"town": "City of Rochester", "url": "http://rocwiki.org/Starry_Nites_Cafe", "name": "Starry Nites Cafe"}, {"town": "City of Rochester", "url": "http://rocwiki.org/Bay_Goodman_Pizza", "name": "Bay Goodman Pizza"}, {"town": "City of Rochester", "url": "http://rocwiki.org/Balsam_Bagels", "name": "Balsam Bagels"}, {"town": "City of Rochester", "url": "http://rocwiki.org/Captain_Jim%27s", "name": "Captain Jim's"}, {"town": "City of Rochester", "url": "http://rocwiki.org/Captain_Tony%27s_Pizza_%26_Pasta_Emporium", "name": "Captain Tony's Pizza & Pasta Emporium"}, {"town": "City of Rochester", "url": "http://rocwiki.org/Carroll%27s_Bar_and_Restaurant", "name": "Carroll's Bar and Restaurant"}, {"town": "City of Rochester", "url": "http://rocwiki.org/China_Garden_Kitchen", "name": "China Garden Kitchen"}, {"town": "City of Rochester", "url": "http://rocwiki.org/Golden_Fox_Restaurant", "name": "Golden Fox Restaurant"}, {"town": "City of Rochester", "url": "http://rocwiki.org/Greenhouse_Cafe", "name": "Greenhouse Cafe"}, {"town": "City of Rochester", "url": "http://rocwiki.org/James_Brown%27s", "name": "James Brown's"}, {"town": "City of Rochester", "url": "http://rocwiki.org/Jim%27s_Restaurant", "name": "Jim's Restaurant"}, {"town": "City of Rochester", "url": "http://rocwiki.org/Liberty_Family_Restaurant", "name": "Liberty Family Restaurant"}, {"town": "City of Rochester", "url": "http://rocwiki.org/Morningstar_Restaurant", "name": "Morningstar Restaurant"}, {"town": "City of Rochester", "url": "http://rocwiki.org/Nino%27s_Pizzeria_and_Focacceria", "name": "Nino's Pizzeria and Focacceria"}, {"town": "City of Rochester", "url": "http://rocwiki.org/Pasta_Chef_To_Go", "name": "Pasta Chef To Go"}, {"town": "City of Rochester", "url": "http://rocwiki.org/Remington%27s", "name": "Remington's"}, {"town": "City of Rochester", "url": "http://rocwiki.org/Rhino%27s_Pizzeria_%26_Deli", "name": "Rhino's Pizzeria & Deli"}, {"town": "City of Rochester", "url": "http://rocwiki.org/Rizzi%27s_Restaurant_and_Bar", "name": "Rizzi's Restaurant and Bar"}, {"town": "City of Rochester", "url": "http://rocwiki.org/Rochester_Hots", "name": "Rochester Hots"}, {"town": "City of Rochester", "url": "http://rocwiki.org/Salvatore%27s_Old_Fashioned_Pizzeria", "name": "Salvatore's Old Fashioned Pizzeria"}, {"town": "City of Rochester", "url": "http://rocwiki.org/Winfield_Grill", "name": "Winfield Grill"}, {"town": "City of Rochester", "url": "http://rocwiki.org/Wintonaire", "name": "Wintonaire"}, {"town": "City of Rochester", "url": "http://rocwiki.org/Culver_Hots", "name": "Culver Hots"}, {"town": "City of Rochester", "url": "http://rocwiki.org/Domino%27s", "name": "Domino's"}, {"town": "City of Rochester", "url": "http://rocwiki.org/Donuts_Delite", "name": "Donuts Delite"}, {"town": "City of Rochester", "url": "http://rocwiki.org/Dunkin%27_Donuts", "name": "Dunkin' Donuts"}, {"town": "City of Rochester", "url": "http://rocwiki.org/Gregorio%27s", "name": "Gregorio's"}, {"town": "City of Rochester", "url": "http://rocwiki.org/Pudgie%27s_Pizza", "name": "Pudgie's Pizza"}, {"town": "City of Rochester", "url": "http://rocwiki.org/Riccardo%27s_Italian_Bakery", "name": "Riccardo's Italian Bakery"}, {"town": "City of Rochester", "url": "http://rocwiki.org/Bacco%27s_Ristorante", "name": "Bacco's Ristorante"}, {"town": "City of Rochester", "url": "http://rocwiki.org/Blu_Wolf_Bistro", "name": "Blu Wolf Bistro"}, {"town": "City of Rochester", "url": "http://rocwiki.org/Boulder_Coffee_Co.", "name": "Boulder Coffee Co."}, {"town": "City of Rochester", "url": "http://rocwiki.org/Charlie%27s_Frog_Pond", "name": "Charlie's Frog Pond"}, {"town": "City of Rochester", "url": "http://rocwiki.org/Cheese_Masters", "name": "Cheese Masters"}, {"town": "City of Rochester", "url": "http://rocwiki.org/Chester_Cab_Pizza", "name": "Chester Cab Pizza"}, {"town": "City of Rochester", "url": "http://rocwiki.org/Cibon", "name": "Cibon"}, {"town": "City of Rochester", "url": "http://rocwiki.org/Dorado", "name": "Dorado"}, {"town": "City of Rochester", "url": "http://rocwiki.org/Esan", "name": "Esan"}, {"town": "City of Rochester", "url": "http://rocwiki.org/French_Quarter_Cafe", "name": "French Quarter Cafe"}, {"town": "City of Rochester", "url": "http://rocwiki.org/Furoshiki", "name": "Furoshiki"}, {"town": "City of Rochester", "url": "http://rocwiki.org/Great_Harvest_Bread_Company", "name": "Great Harvest Bread Company"}, {"town": "City of Rochester", "url": "http://rocwiki.org/Hogans_Hideaway", "name": "Hogans Hideaway"}, {"town": "City of Rochester", "url": "http://rocwiki.org/Jembetat_Gallery_and_Cafe", "name": "Jembetat Gallery and Cafe"}, {"town": "City of Rochester", "url": "http://rocwiki.org/Jine%27s", "name": "Jine's"}, {"town": "City of Rochester", "url": "http://rocwiki.org/Just_Juice", "name": "Just Juice"}, {"town": "City of Rochester", "url": "http://rocwiki.org/La-Tea-Da%21_Tea_Room_and_Parlour", "name": "La-Tea-Da! Tea Room and Parlour"}, {"town": "City of Rochester", "url": "http://rocwiki.org/Magnolia%27s_Deli_%26_Cafe", "name": "Magnolia's Deli & Cafe"}, {"town": "City of Rochester", "url": "http://rocwiki.org/Magpie", "name": "Magpie"}, {"town": "City of Rochester", "url": "http://rocwiki.org/Marvin_Mozzeroni%27s", "name": "Marvin Mozzeroni's"}, {"town": "City of Rochester", "url": "http://rocwiki.org/Nathan%27s_Soup_%26_Salad", "name": "Nathan's Soup & Salad"}, {"town": "City of Rochester", "url": "http://rocwiki.org/Park_Avenue_Pub", "name": "Park Avenue Pub"}, {"town": "City of Rochester", "url": "http://rocwiki.org/The_Red_Fern", "name": "The Red Fern"}, {"town": "City of Rochester", "url": "http://rocwiki.org/Roam_Cafe", "name": "Roam Cafe"}, {"town": "City of Rochester", "url": "http://rocwiki.org/Sinbad%27s", "name": "Sinbad's"}, {"town": "City of Rochester", "url": "http://rocwiki.org/Deli_Sandros", "name": "Deli Sandros"}, {"town": "City of Rochester", "url": "http://rocwiki.org/Kneel_%26_Neal_Southern_Cuisine", "name": "Kneel & Neal Southern Cuisine"}, {"town": "City of Rochester", "url": "http://rocwiki.org/Banzai_Sushi_Bar_%26_Lounge", "name": "Banzai Sushi Bar & Lounge"}, {"town": "City of Rochester", "url": "http://rocwiki.org/Beale_Street_Cafe", "name": "Beale Street Cafe"}, {"town": "City of Rochester", "url": "http://rocwiki.org/Boulder_Coffee_Co.", "name": "Boulder Coffee Co."}, {"town": "City of Rochester", "url": "http://rocwiki.org/Cheshire", "name": "Cheshire"}, {"town": "City of Rochester", "url": "http://rocwiki.org/Equal_Grounds", "name": "Equal Grounds"}, {"town": "City of Rochester", "url": "http://rocwiki.org/Harry_G%27s_NY_Deli_%26_Cafe", "name": "Harry G's NY Deli & Cafe"}, {"town": "City of Rochester", "url": "http://rocwiki.org/John%27s_Tex-Mex_Eatery", "name": "John's Tex-Mex Eatery"}, {"town": "City of Rochester", "url": "http://rocwiki.org/La_Casa_Restaurant", "name": "La Casa Restaurant"}, {"town": "City of Rochester", "url": "http://rocwiki.org/Lin%27s_Garden", "name": "Lin's Garden"}, {"town": "City of Rochester", "url": "http://rocwiki.org/Little_Venice_Pizza", "name": "Little Venice Pizza"}, {"town": "City of Rochester", "url": "http://rocwiki.org/Mise_en_Place_Market", "name": "Mise en Place Market"}, {"town": "City of Rochester", "url": "http://rocwiki.org/Napa_Wood_Fired_Pizzeria", "name": "Napa Wood Fired Pizzeria"}, {"town": "City of Rochester", "url": "http://rocwiki.org/Open_Face_Sandwich_Eatery", "name": "Open Face Sandwich Eatery"}, {"town": "City of Rochester", "url": "http://rocwiki.org/Pat%27s_Coffee_Mug", "name": "Pat's Coffee Mug"}, {"town": "City of Rochester", "url": "http://rocwiki.org/Peppa_Pot_Restaurant", "name": "Peppa Pot Restaurant"}, {"town": "City of Rochester", "url": "http://rocwiki.org/Savory_Thyme", "name": "Savory Thyme"}, {"town": "City of Rochester", "url": "http://rocwiki.org/White_Swans_Asia_Caffe", "name": "White Swans Asia Caffe"}, {"town": "City of Rochester", "url": "http://rocwiki.org/Zeppa_Bistro", "name": "Zeppa Bistro"}, {"town": "City of Rochester", "url": "http://rocwiki.org/1872_Cafe", "name": "1872 Cafe"}, {"town": "City of Rochester", "url": "http://rocwiki.org/China_Star", "name": "China Star"}, {"town": "City of Rochester", "url": "http://rocwiki.org/Golden_Unicorn", "name": "Golden Unicorn"}, {"town": "City of Rochester", "url": "http://rocwiki.org/MJ_Daily_Bread", "name": "MJ Daily Bread"}, {"town": "City of Rochester", "url": "http://rocwiki.org/Mattie%E2%80%99s_Restaurant_and_Bakery", "name": "Mattie\u2019s Restaurant and Bakery"}, {"town": "City of Rochester", "url": "http://rocwiki.org/Nick_Tahou%27s", "name": "Nick Tahou's"}, {"town": "City of Rochester", "url": "http://rocwiki.org/Antonetta%27s_Restaurant", "name": "Antonetta's Restaurant"}, {"town": "City of Rochester", "url": "http://rocwiki.org/Salvatore%27s_Old_Fashioned_Pizzeria", "name": "Salvatore's Old Fashioned Pizzeria"}, {"town": "City of Rochester", "url": "http://rocwiki.org/Subway_Restaurants", "name": "Subway"}, {"town": "City of Rochester", "url": "http://rocwiki.org/Tim_Hortons", "name": "Tim Hortons"}, {"town": "City of Rochester", "url": "http://rocwiki.org/Wilshire_Restaurant_%26_Catering", "name": "Wilshire Restaurant & Catering"}, {"town": "City of Rochester", "url": "http://rocwiki.org/Dee%27s_Model_Diner", "name": "Dee's Model Diner"}, {"town": "City of Rochester", "url": "http://rocwiki.org/Genesee_Brew_House", "name": "Genesee Brew House"}, {"town": "City of Rochester", "url": "http://rocwiki.org/McDonald%27s", "name": "McDonald's"}, {"town": "City of Rochester", "url": "http://rocwiki.org/New_Ming", "name": "New Ming"}, {"town": "City of Rochester", "url": "http://rocwiki.org/TRATA", "name": "TRATA"}, {"town": "City of Rochester", "url": "http://rocwiki.org/Abyssinia", "name": "Abyssinia"}, {"town": "City of Rochester", "url": "http://rocwiki.org/Bruegger%27s", "name": "Bruegger's"}, {"town": "City of Rochester", "url": "http://rocwiki.org/Bunga_Burger_Bar", "name": "Bunga Burger Bar"}, {"town": "City of Rochester", "url": "http://rocwiki.org/Burger_King", "name": "Burger King"}, {"town": "City of Rochester", "url": "http://rocwiki.org/Chipotle_Mexican_Grill", "name": "Chipotle Mexican Grill"}, {"town": "City of Rochester", "url": "http://rocwiki.org/Country_Sweet", "name": "Country Sweet"}, {"town": "City of Rochester", "url": "http://rocwiki.org/Domino%27s", "name": "Domino's"}, {"town": "City of Rochester", "url": "http://rocwiki.org/Dunkin%27_Donuts", "name": "Dunkin' Donuts"}, {"town": "City of Rochester", "url": "http://rocwiki.org/Jing_Li", "name": "Jing Li"}, {"town": "City of Rochester", "url": "http://rocwiki.org/McDonald%27s", "name": "McDonald's"}, {"town": "City of Rochester", "url": "http://rocwiki.org/Mr._Shoes", "name": "Mr. Shoes"}, {"town": "City of Rochester", "url": "http://rocwiki.org/Mt._Hope_Diner", "name": "Mt. Hope Diner"}, {"town": "City of Rochester", "url": "http://rocwiki.org/New_Number_One", "name": "New Number One"}, {"town": "City of Rochester", "url": "http://rocwiki.org/Pontillo%27s", "name": "Pontillo's"}, {"town": "City of Rochester", "url": "http://rocwiki.org/Rubino%27s", "name": "Rubino's"}, {"town": "City of Rochester", "url": "http://rocwiki.org/SEA_Restaurant", "name": "SEA Restaurant"}, {"town": "City of Rochester", "url": "http://rocwiki.org/Sheridan%27s_Pub", "name": "Sheridan's Pub"}, {"town": "City of Rochester", "url": "http://rocwiki.org/Subway_Restaurants", "name": "Subway"}, {"town": "City of Rochester", "url": "http://rocwiki.org/Sultan", "name": "Sultan"}, {"town": "City of Rochester", "url": "http://rocwiki.org/Wendy%27s", "name": "Wendy's"}, {"town": "City of Rochester", "url": "http://rocwiki.org/Marshall_Street_Bar_and_Grill", "name": "Marshall Street Bar and Grill"}, {"town": "City of Rochester", "url": "http://rocwiki.org/The_Owl_House", "name": "The Owl House"}, {"town": "City of Rochester", "url": "http://rocwiki.org/Rocco", "name": "Rocco"}, {"town": "Chili", "url": "http://rocwiki.org/China_King", "name": "China King"}, {"town": "Chili", "url": "http://rocwiki.org/Colombini%27s_Deli", "name": "Colombini's Deli"}, {"town": "Chili", "url": "http://rocwiki.org/Golden_Garden", "name": "Golden Garden"}, {"town": "Chili", "url": "http://rocwiki.org/Guetti%27s_Pizza_%26_Subs", "name": "Guetti's Pizza & Subs"}, {"town": "Chili", "url": "http://rocwiki.org/Itacate", "name": "Itacate"}, {"town": "Chili", "url": "http://rocwiki.org/Jet_Diner", "name": "Jet Diner"}, {"town": "Chili", "url": "http://rocwiki.org/Nick%27s_Pizza_%26_Subs", "name": "Nick's Pizza & Subs"}, {"town": "Chili", "url": "http://rocwiki.org/North_Chili_Family_Restaurant", "name": "North Chili Family Restaurant"}, {"town": "Chili", "url": "http://rocwiki.org/Phil%27s_Pizza", "name": "Phil's Pizza"}, {"town": "Chili", "url": "http://rocwiki.org/Pontillo%27s", "name": "Pontillo's"}, {"town": "Chili", "url": "http://rocwiki.org/Six50", "name": "Six50"}, {"town": "Chili", "url": "http://rocwiki.org/Sylvio%27s_Pizzeria_and_Catering", "name": "Sylvio's Pizzeria and Catering"}, {"town": "Chili", "url": "http://rocwiki.org/Town_and_Country_Family_Restaurant", "name": "Town and Country Family Restaurant"}, {"town": "Chili", "url": "http://rocwiki.org/Good_Guys_Pizza", "name": "Good Guys Pizza"}, {"town": "Chili", "url": "http://rocwiki.org/Acropolis_Restaurant", "name": "Acropolis Restaurant"}, {"town": "Chili", "url": "http://rocwiki.org/Bill_Gray%27s", "name": "Bill Gray's"}, {"town": "Chili", "url": "http://rocwiki.org/Osaka_Sushi", "name": "Osaka Sushi"}, {"town": "Chili", "url": "http://rocwiki.org/Subway_Restaurants", "name": "Subway Restaurants"}, {"town": "East Rochester", "url": "http://rocwiki.org/Bistro_135", "name": "Bistro 135"}, {"town": "East Rochester", "url": "http://rocwiki.org/Crust_Pizza_Kitchen", "name": "Crust Pizza Kitchen"}, {"town": "East Rochester", "url": "http://rocwiki.org/Good_Smoke_BBQ", "name": "Good Smoke BBQ"}, {"town": "East Rochester", "url": "http://rocwiki.org/Lemoncello_Italian_Restaurant_%26_Bar", "name": "Lemoncello Italian Restaurant & Bar"}, {"town": "East Rochester", "url": "http://rocwiki.org/Leo%27s_Elite_Bakery", "name": "Leo's Elite Bakery"}, {"town": "East Rochester", "url": "http://rocwiki.org/McGraw%27s_Irish_Pub", "name": "McGraw's Irish Pub"}, {"town": "East Rochester", "url": "http://rocwiki.org/New_Yorker%27s", "name": "New Yorker's"}, {"town": "East Rochester", "url": "http://rocwiki.org/Northside_Inn", "name": "Northside Inn"}, {"town": "East Rochester", "url": "http://rocwiki.org/Pellegrino%27s_Deli_Cafe", "name": "Pellegrino's Deli Cafe"}, {"town": "East Rochester", "url": "http://rocwiki.org/Perlo%27s", "name": "Perlo's"}, {"town": "East Rochester", "url": "http://rocwiki.org/Roma%27s_Italian_Cafe", "name": "Roma's Italian Cafe"}, {"town": "East Rochester", "url": "http://rocwiki.org/Rubino%27s", "name": "Rubino's"}, {"town": "East Rochester", "url": "http://rocwiki.org/Salvatore%27s_Old_Fashioned_Pizzeria", "name": "Salvatore's Old Fashioned Pizzeria"}, {"town": "East Rochester", "url": "http://rocwiki.org/Surace%27s_Pizza_%26_Subs", "name": "Surace's Pizza & Subs"}, {"town": "East Rochester", "url": "http://rocwiki.org/Take-A-Break_Family_Restaurant", "name": "Take-A-Break Family Restaurant"}, {"town": "East Rochester", "url": "http://rocwiki.org/Village_Way_Pizzeria", "name": "Village Way Pizzeria"}, {"town": "East Rochester", "url": "http://rocwiki.org/Wendy%27s", "name": "Wendy's"}, {"town": "Fairport / Perinton", "url": "http://rocwiki.org/Aja_Noodle_Company", "name": "Aja Noodle Company"}, {"town": "Fairport / Perinton", "url": "http://rocwiki.org/Applebee%27s", "name": "Applebee's"}, {"town": "Fairport / Perinton", "url": "http://rocwiki.org/Argyle_Grill", "name": "Argyle Grill"}, {"town": "Fairport / Perinton", "url": "http://rocwiki.org/The_Basin_Pub", "name": "The Basin Pub"}, {"town": "Fairport / Perinton", "url": "http://rocwiki.org/Big_Al%27s_Empanada_Express", "name": "Big Al's Empanada Express"}, {"town": "Fairport / Perinton", "url": "http://rocwiki.org/Bill_Gray%27s", "name": "Bill Gray's"}, {"town": "Fairport / Perinton", "url": "http://rocwiki.org/Bistro_Han", "name": "Bistro Han"}, {"town": "Fairport / Perinton", "url": "http://rocwiki.org/Blue_Cactus_Mexican_Grille", "name": "Blue Cactus Mexican Grille"}, {"town": "Fairport / Perinton", "url": "http://rocwiki.org/Bocaccinis", "name": "Bocaccinis"}, {"town": "Fairport / Perinton", "url": "http://rocwiki.org/Bruegger%27s", "name": "Bruegger's"}, {"town": "Fairport / Perinton", "url": "http://rocwiki.org/The_Cellar_Door", "name": "The Cellar Door"}, {"town": "Fairport / Perinton", "url": "http://rocwiki.org/Chakara_Bistro_%26_Bar", "name": "Chakara Bistro & Bar"}, {"town": "Fairport / Perinton", "url": "http://rocwiki.org/China_King_%28Fairport%29", "name": "China King (Fairport)"}, {"town": "Fairport / Perinton", "url": "http://rocwiki.org/Clawson%27s_Deli_and_Grocery", "name": "Clawson's Deli and Grocery"}, {"town": "Fairport / Perinton", "url": "http://rocwiki.org/Compane_Brick_Oven_Bistro", "name": "Compane Brick Oven Bistro"}, {"town": "Fairport / Perinton", "url": "http://rocwiki.org/Costello%27s_Pizza_Emporium", "name": "Costello's Pizza Emporium"}, {"town": "Fairport / Perinton", "url": "http://rocwiki.org/Denny%27s", "name": "Denny's"}, {"town": "Fairport / Perinton", "url": "http://rocwiki.org/DiBella%27s", "name": "DiBella's"}, {"town": "Fairport / Perinton", "url": "http://rocwiki.org/Donnelly%27s_Public_House", "name": "Donnelly's Public House"}, {"town": "Fairport / Perinton", "url": "http://rocwiki.org/Durf%27s_Family_Restaurant", "name": "Durf's Family Restaurant"}, {"town": "Fairport / Perinton", "url": "http://rocwiki.org/Eastside_Cafe", "name": "Eastside Cafe"}, {"town": "Fairport / Perinton", "url": "http://rocwiki.org/Fairfields_Grill", "name": "Fairfields Grill"}, {"town": "Fairport / Perinton", "url": "http://rocwiki.org/Fairport_Hots", "name": "Fairport Hots"}, {"town": "Fairport / Perinton", "url": "http://rocwiki.org/Fairport_Village_Inn", "name": "Fairport Village Inn"}, {"town": "Fairport / Perinton", "url": "http://rocwiki.org/Glengarry_Inn", "name": "Glengarry Inn"}, {"town": "Fairport / Perinton", "url": "http://rocwiki.org/Golden_Phoenix", "name": "Golden Phoenix"}, {"town": "Fairport / Perinton", "url": "http://rocwiki.org/Headliners_Pizza", "name": "Headliners Pizza"}, {"town": "Fairport / Perinton", "url": "http://rocwiki.org/Horizons", "name": "Horizons"}, {"town": "Fairport / Perinton", "url": "http://rocwiki.org/J_%26_L%27s_Pizza_Korner", "name": "J & L's Pizza Korner"}, {"town": "Fairport / Perinton", "url": "http://rocwiki.org/Joey_B%27s", "name": "Joey B's"}, {"town": "Fairport / Perinton", "url": "http://rocwiki.org/Jozeppi%27s_Pizzeria", "name": "Jozeppi's Pizzeria"}, {"town": "Fairport / Perinton", "url": "http://rocwiki.org/The_Landing_Bar_and_Grille", "name": "Landing Bar and Grille, The"}, {"town": "Fairport / Perinton", "url": "http://rocwiki.org/Mac%27s_Philly_Steaks", "name": "Mac's Philly Steaks"}, {"town": "Fairport / Perinton", "url": "http://rocwiki.org/Mark%27s_Pizzeria", "name": "Mark's Pizzeria"}, {"town": "Fairport / Perinton", "url": "http://rocwiki.org/McArdle%27s", "name": "McArdle's"}, {"town": "Fairport / Perinton", "url": "http://rocwiki.org/McDonald%27s", "name": "McDonald's"}, {"town": "Fairport / Perinton", "url": "http://rocwiki.org/Mulconry%27s", "name": "Mulconry's"}, {"town": "Fairport / Perinton", "url": "http://rocwiki.org/Napa_Wood_Fired_Pizzeria", "name": "Napa Wood Fired Pizzeria"}, {"town": "Fairport / Perinton", "url": "http://rocwiki.org/Panera_Bread", "name": "Panera Bread"}, {"town": "Fairport / Perinton", "url": "http://rocwiki.org/Papa_John%27s", "name": "Papa John's"}, {"town": "Fairport / Perinton", "url": "http://rocwiki.org/Perinton_Pizza", "name": "Perinton Pizza"}, {"town": "Fairport / Perinton", "url": "http://rocwiki.org/The_Pizza_Chef", "name": "Pizza Chef, The"}, {"town": "Fairport / Perinton", "url": "http://rocwiki.org/Pontillo%27s", "name": "Pontillo's"}, {"town": "Fairport / Perinton", "url": "http://rocwiki.org/Rene%27s_Cafe", "name": "Rene's Cafe"}, {"town": "Fairport / Perinton", "url": "http://rocwiki.org/Royal_Cafe", "name": "Royal Cafe"}, {"town": "Fairport / Perinton", "url": "http://rocwiki.org/Riki%27s_Family_Restaurant", "name": "Riki's Family Restaurant"}, {"town": "Fairport / Perinton", "url": "http://rocwiki.org/Sak%27s_Thai_Cuisine", "name": "Sak's Thai Cuisine"}, {"town": "Fairport / Perinton", "url": "http://rocwiki.org/Sakura_Garden", "name": "Sakura Garden"}, {"town": "Fairport / Perinton", "url": "http://rocwiki.org/salvatore%27s", "name": "Salvatore's"}, {"town": "Fairport / Perinton", "url": "http://rocwiki.org/Shooters_Sports_Bar_%26_Grill", "name": "Shooters Sports Bar & Grill"}, {"town": "Fairport / Perinton", "url": "http://rocwiki.org/Shorts_Bar_and_Grill", "name": "Shorts Bar and Grill"}, {"town": "Fairport / Perinton", "url": "http://rocwiki.org/T.K.%27s_Pizzeria", "name": "T.K.'s Pizzeria"}, {"town": "Fairport / Perinton", "url": "http://rocwiki.org/Tom_Wahl%27s", "name": "Tom Wahl's"}, {"town": "Fairport / Perinton", "url": "http://rocwiki.org/Towpath_Cafe", "name": "Towpath Cafe"}, {"town": "Fairport / Perinton", "url": "http://rocwiki.org/TR_Noonan%27s", "name": "TR Noonan's"}, {"town": "Fairport / Perinton", "url": "http://rocwiki.org/Vinny%27s_Bakery_%26_Deli", "name": "Vinny's Bakery & Deli"}, {"town": "Fairport / Perinton", "url": "http://rocwiki.org/Wendy%27s", "name": "Wendy's"}, {"town": "Gates", "url": "http://rocwiki.org/Agatina%27s", "name": "Agatina's"}, {"town": "Gates", "url": "http://rocwiki.org/Applebee%27s", "name": "Applebee's"}, {"town": "Gates", "url": "http://rocwiki.org/Blu_Bar_%26_Grill", "name": "Blu Bar & Grill"}, {"town": "Gates", "url": "http://rocwiki.org/Calabria%27s", "name": "Calabria's"}, {"town": "Gates", "url": "http://rocwiki.org/China_Wok", "name": "China Wok"}, {"town": "Gates", "url": "http://rocwiki.org/Delinda%27s", "name": "Delinda's"}, {"town": "Gates", "url": "http://rocwiki.org/Delta_House", "name": "Delta House"}, {"town": "Gates", "url": "http://rocwiki.org/Edoya", "name": "Edoya"}, {"town": "Gates", "url": "http://rocwiki.org/Elm_Grove_Family_Restaurant", "name": "Elm Grove Family Restaurant"}, {"town": "Gates", "url": "http://rocwiki.org/Ezzy%27s_Restaurant", "name": "Ezzy's Restaurant"}, {"town": "Gates", "url": "http://rocwiki.org/Fiamma", "name": "Fiamma"}, {"town": "Gates", "url": "http://rocwiki.org/Giuseppe%27s", "name": "Giuseppe's"}, {"town": "Gates", "url": "http://rocwiki.org/The_Infield", "name": "The Infield"}, {"town": "Gates", "url": "http://rocwiki.org/Jack%27ss_BBQ_%26_Pizza", "name": "Jack'ss BBQ & Pizza"}, {"town": "Gates", "url": "http://rocwiki.org/Mac%27s_Pizzeria_%26_Grill", "name": "Mac's Pizzeria & Grill"}, {"town": "Gates", "url": "http://rocwiki.org/Martino%27s_Restaurant", "name": "Martino's Restaurant"}, {"town": "Gates", "url": "http://rocwiki.org/Mr._Beenz_Diner", "name": "Mr. Beenz Diner"}, {"town": "Gates", "url": "http://rocwiki.org/Olympia_Family_Restaurant", "name": "Olympia Family Restaurant"}, {"town": "Gates", "url": "http://rocwiki.org/Palermo%27s_Subs_%26_Pizza", "name": "Palermo's Subs & Pizza"}, {"town": "Gates", "url": "http://rocwiki.org/Papa_Joe%27s_Italian_Eatery", "name": "Papa Joe's Italian Eatery"}, {"town": "Gates", "url": "http://rocwiki.org/Perri%27s_Pizzeria", "name": "Perri's Pizzeria"}, {"town": "Gates", "url": "http://rocwiki.org/Pixley%27s", "name": "Pixley's"}, {"town": "Gates", "url": "http://rocwiki.org/Rick%27s_Prime_Rib_House", "name": "Rick's Prime Rib House"}, {"town": "Gates", "url": "http://rocwiki.org/Rohrbach_Brewery", "name": "Rohrbach Brewery"}, {"town": "Gates", "url": "http://rocwiki.org/Rookies_Neighborhood_Sports_Bar", "name": "Rookies Neighborhood Sports Bar"}, {"town": "Gates", "url": "http://rocwiki.org/Savastano%27s_Pizzeria_%26_Bakery", "name": "Savastano's Pizzeria & Bakery"}, {"town": "Gates", "url": "http://rocwiki.org/Westgate_Family_Restaurant", "name": "Westgate Family Restaurant"}, {"town": "Gates", "url": "http://rocwiki.org/Wimpy%27s_Burger_Basket", "name": "Wimpy's Burger Basket"}, {"town": "Gates", "url": "http://rocwiki.org/Yianni%27s_Steak_and_Steakfood", "name": "Yianni's Steak and Steakfood"}, {"town": "Greece", "url": "http://rocwiki.org/Alfano%27s", "name": "Alfano's"}, {"town": "Greece", "url": "http://rocwiki.org/Bathtub_Billy%27s", "name": "Bathtub Billy's"}, {"town": "Greece", "url": "http://rocwiki.org/Bella_Pasta_Cafe", "name": "Bella Pasta Cafe"}, {"town": "Greece", "url": "http://rocwiki.org/Bernard%27s_Grove", "name": "Bernard's Grove"}, {"town": "Greece", "url": "http://rocwiki.org/Blue_Ocean_Japanese_Restaurant", "name": "Blue Ocean Japanese Restaurant"}, {"town": "Greece", "url": "http://rocwiki.org/Chili%27s", "name": "Chili's"}, {"town": "Greece", "url": "http://rocwiki.org/China_Buffet", "name": "China Buffet"}, {"town": "Greece", "url": "http://rocwiki.org/Davinci_of_Greece", "name": "Davinci of Greece"}, {"town": "Greece", "url": "http://rocwiki.org/Delinda%27s", "name": "Delinda's"}, {"town": "Greece", "url": "http://rocwiki.org/Famous_Dave%27s", "name": "Famous Dave's"}, {"town": "Greece", "url": "http://rocwiki.org/Forklift_Cafe", "name": "Forklift Cafe"}, {"town": "Greece", "url": "http://rocwiki.org/Fu_Lin_Chinese_Kitchen", "name": "Fu Lin Chinese Kitchen"}, {"town": "Greece", "url": "http://rocwiki.org/Gallo%27s_Pizza_%26_Subs", "name": "Gallo's Pizza & Subs"}, {"town": "Greece", "url": "http://rocwiki.org/Grande_Amore_Pizza", "name": "Grande Amore Pizza"}, {"town": "Greece", "url": "http://rocwiki.org/Grand_Super_Buffet", "name": "Grand Super Buffet"}, {"town": "Greece", "url": "http://rocwiki.org/Greece_China", "name": "Greece China"}, {"town": "Greece", "url": "http://rocwiki.org/Greece_Ridge_Family_Restaurant", "name": "Greece Ridge Family Restaurant"}, {"town": "Greece", "url": "http://rocwiki.org/International_Buffet", "name": "International Buffet"}, {"town": "Greece", "url": "http://rocwiki.org/Kip%27s_Pizzeria_Americana", "name": "Kip's Pizzeria Americana"}, {"town": "Greece", "url": "http://rocwiki.org/Kobe_Steak_House", "name": "Kobe Steak House"}, {"town": "Greece", "url": "http://rocwiki.org/La_Famiglia_Pizzeria", "name": "La Famiglia Pizzeria"}, {"town": "Greece", "url": "http://rocwiki.org/The_Lamplighter_Restaurant", "name": "The Lamplighter Restaurant"}, {"town": "Greece", "url": "http://rocwiki.org/Long_Pond_Family_Restaurant", "name": "Long Pond Family Restaurant"}, {"town": "Greece", "url": "http://rocwiki.org/Los_Gallos", "name": "Los Gallos"}, {"town": "Greece", "url": "http://rocwiki.org/Marvin_Mozzeroni%27s", "name": "Marvin Mozzeroni's"}, {"town": "Greece", "url": "http://rocwiki.org/Masters_Seafood", "name": "Masters Seafood"}, {"town": "Greece", "url": "http://rocwiki.org/Mel%27s_Diner", "name": "Mel's Diner"}, {"town": "Greece", "url": "http://rocwiki.org/New_Fong_Kitchen", "name": "New Fong Kitchen"}, {"town": "Greece", "url": "http://rocwiki.org/Olympia_Restaurant", "name": "Olympia Restaurant"}, {"town": "Greece", "url": "http://rocwiki.org/Oriens_Cafe", "name": "Oriens Cafe"}, {"town": "Greece", "url": "http://rocwiki.org/Outback_Steakhouse", "name": "Outback Steakhouse"}, {"town": "Greece", "url": "http://rocwiki.org/Perri%27s_Pizzeria", "name": "Perri's Pizzeria"}, {"town": "Greece", "url": "http://rocwiki.org/Pino%27s_Deli", "name": "Pino's Deli"}, {"town": "Greece", "url": "http://rocwiki.org/Pizza_Stop", "name": "Pizza Stop"}, {"town": "Greece", "url": "http://rocwiki.org/Red_Lobster", "name": "Red Lobster"}, {"town": "Greece", "url": "http://rocwiki.org/Ricci%27s_Family_Restaurant", "name": "Ricci's Family Restaurant"}, {"town": "Greece", "url": "http://rocwiki.org/Romeo%27s", "name": "Romeo's"}, {"town": "Greece", "url": "http://rocwiki.org/Russo%27s_Clubhouse_Pizza", "name": "Russo's Clubhouse Pizza"}, {"town": "Greece", "url": "http://rocwiki.org/Taco_Bell", "name": "Taco Bell"}, {"town": "Greece", "url": "http://rocwiki.org/Ting_Ho", "name": "Ting Ho"}, {"town": "Greece", "url": "http://rocwiki.org/Tom_%26_Nancy%27s_Pizza", "name": "Tom & Nancy's Pizza"}, {"town": "Greece", "url": "http://rocwiki.org/Tony%27s_Birdland_%26_Pizzeria", "name": "Tony's Birdland & Pizzeria"}, {"town": "Greece", "url": "http://rocwiki.org/Trotto%27s_Pizzeria", "name": "Trotto's Pizzeria"}, {"town": "Greece", "url": "http://rocwiki.org/Uncle_Eddie%27s_Pizzeria", "name": "Uncle Eddie's Pizzeria"}, {"town": "Greece", "url": "http://rocwiki.org/Valicia%27s_Ristorante", "name": "Valicia's Ristorante"}, {"town": "Greece", "url": "http://rocwiki.org/Wise_Guys_Diner", "name": "Wise Guys Diner"}, {"town": "Greece", "url": "http://rocwiki.org/Chinatown_Restaurant", "name": "Chinatown Restaurant"}, {"town": "Greece", "url": "http://rocwiki.org/Red_Fedele%27s_Brook_House", "name": "Red Fedele's Brook House"}, {"town": "Greece", "url": "http://rocwiki.org/Taco_Bell", "name": "Taco Bell"}, {"town": "Greece", "url": "http://rocwiki.org/Century_Buffet_King", "name": "Century Buffet King"}, {"town": "Greece", "url": "http://rocwiki.org/Critics_on_the_Mall", "name": "Critics on the Mall"}, {"town": "Greece", "url": "http://rocwiki.org/Friendly%27s", "name": "Friendly's"}, {"town": "Greece", "url": "http://rocwiki.org/Panera_Bread", "name": "Panera Bread"}, {"town": "Greece", "url": "http://rocwiki.org/Sarku_Japan", "name": "Sarku Japan"}, {"town": "Greece", "url": "http://rocwiki.org/Sbarro", "name": "Sbarro"}, {"town": "Greece", "url": "http://rocwiki.org/TGI_Friday%27s", "name": "TGI Friday's"}, {"town": "Greece", "url": "http://rocwiki.org/Old_Country_Buffet", "name": "Old Country Buffet"}, {"town": "Henrietta", "url": "http://rocwiki.org/Amiel%27s", "name": "Amiel's"}, {"town": "Henrietta", "url": "http://rocwiki.org/Bombay_Chaat_House", "name": "Bombay Chaat House"}, {"town": "Henrietta", "url": "http://rocwiki.org/Boston_Market", "name": "Boston Market"}, {"town": "Henrietta", "url": "http://rocwiki.org/Bugaboo_Creek", "name": "Bugaboo Creek"}, {"town": "Henrietta", "url": "http://rocwiki.org/Carrabba%27s_Italian_Grill", "name": "Carrabba's Italian Grill"}, {"town": "Henrietta", "url": "http://rocwiki.org/Chili%27s", "name": "Chili's"}, {"town": "Henrietta", "url": "http://rocwiki.org/China_Garden", "name": "China Garden"}, {"town": "Henrietta", "url": "http://rocwiki.org/Cosimos_Pizza", "name": "Cosimos Pizza"}, {"town": "Henrietta", "url": "http://rocwiki.org/Cracker_Barrel", "name": "Cracker Barrel"}, {"town": "Henrietta", "url": "http://rocwiki.org/Denny%27s", "name": "Denny's"}, {"town": "Henrietta", "url": "http://rocwiki.org/The_Distillery", "name": "The Distillery"}, {"town": "Henrietta", "url": "http://rocwiki.org/El_Dorado_Mexican_Cuisine", "name": "El Dorado Mexican Cuisine"}, {"town": "Henrietta", "url": "http://rocwiki.org/Guys_Pizza_Co.", "name": "Guys Pizza Co."}, {"town": "Henrietta", "url": "http://rocwiki.org/Haveli_Indian_Cuisine", "name": "Haveli Indian Cuisine"}, {"town": "Henrietta", "url": "http://rocwiki.org/IHOP", "name": "IHOP"}, {"town": "Henrietta", "url": "http://rocwiki.org/Infantino%27s_Market_Restaurant", "name": "Infantino's Market Restaurant"}, {"town": "Henrietta", "url": "http://rocwiki.org/Jimmy_John%27s_Gourmet_Sandwiches", "name": "Jimmy John's Gourmet Sandwiches"}, {"town": "Henrietta", "url": "http://rocwiki.org/Kenna%27s_Diner", "name": "Kenna's Diner"}, {"town": "Henrietta", "url": "http://rocwiki.org/King_and_I", "name": "King and I"}, {"town": "Henrietta", "url": "http://rocwiki.org/Joe%27s_Crab_Shack", "name": "Joe's Crab Shack"}, {"town": "Henrietta", "url": "http://rocwiki.org/Ken%27s_Pizza_Corner", "name": "Ken's Pizza Corner"}, {"town": "Henrietta", "url": "http://rocwiki.org/Lucci%27s_Pizza_%26_Grill", "name": "Lucci's Pizza & Grill"}, {"town": "Henrietta", "url": "http://rocwiki.org/Lunch_Box_Spot", "name": "Lunch Box Spot"}, {"town": "Henrietta", "url": "http://rocwiki.org/MacGregor%27s", "name": "MacGregor's"}, {"town": "Henrietta", "url": "http://rocwiki.org/Mariachi_Mexican_Grill", "name": "Mariachi Mexican Grill"}, {"town": "Henrietta", "url": "http://rocwiki.org/Marvin_Mozzeroni%27s", "name": "Marvin Mozzeroni's"}, {"town": "Henrietta", "url": "http://rocwiki.org/The_Melting_Pot", "name": "The Melting Pot"}, {"town": "Henrietta", "url": "http://rocwiki.org/Mighty_Taco", "name": "Mighty Taco"}, {"town": "Henrietta", "url": "http://rocwiki.org/New_Cantonese", "name": "New Cantonese"}, {"town": "Henrietta", "url": "http://rocwiki.org/Nick_Tahou%27s", "name": "Nick Tahou's"}, {"town": "Henrietta", "url": "http://rocwiki.org/Olive_Garden", "name": "Olive Garden"}, {"town": "Henrietta", "url": "http://rocwiki.org/Outback_Steakhouse", "name": "Outback Steakhouse"}, {"town": "Henrietta", "url": "http://rocwiki.org/Papaya_Asian_Kitchen_%26_Bar", "name": "Papaya Asian Kitchen & Bar"}, {"town": "Henrietta", "url": "http://rocwiki.org/Peppermints_Restaurant", "name": "Peppermints Restaurant"}, {"town": "Henrietta", "url": "http://rocwiki.org/Pickle_Nick%27s", "name": "Pickle Nick's"}, {"town": "Henrietta", "url": "http://rocwiki.org/Red_Lobster", "name": "Red Lobster"}, {"town": "Henrietta", "url": "http://rocwiki.org/Salsarita%27s_Fresh_Cantina", "name": "Salsarita's Fresh Cantina"}, {"town": "Henrietta", "url": "http://rocwiki.org/Shanghai", "name": "Shanghai"}, {"town": "Henrietta", "url": "http://rocwiki.org/Sodam_Korean_Restaurant", "name": "Sodam Korean Restaurant"}, {"town": "Henrietta", "url": "http://rocwiki.org/Sticky_Lips_Pit_BBQ", "name": "Sticky Lips Pit BBQ"}, {"town": "Henrietta", "url": "http://rocwiki.org/Taco_Bell", "name": "Taco Bell"}, {"town": "Henrietta", "url": "http://rocwiki.org/Texas_Roadhouse", "name": "Texas Roadhouse"}, {"town": "Henrietta", "url": "http://rocwiki.org/Tim_Hortons", "name": "Tim Hortons"}, {"town": "Henrietta", "url": "http://rocwiki.org/Tokyo_Japanese_Restaurant", "name": "Tokyo Japanese Restaurant"}, {"town": "Henrietta", "url": "http://rocwiki.org/Tony_Pepperoni", "name": "Tony Pepperoni"}, {"town": "Henrietta", "url": "http://rocwiki.org/Uno_Chicago_Grill", "name": "Uno Chicago Grill"}, {"town": "Henrietta", "url": "http://rocwiki.org/Wendy%27s", "name": "Wendy's"}, {"town": "Henrietta", "url": "http://rocwiki.org/Wings_Over_Rochester", "name": "Wings Over Rochester"}, {"town": "Henrietta", "url": "http://rocwiki.org/Young%27s_Korean_Restaurant", "name": "Young's Korean Restaurant"}, {"town": "Henrietta", "url": "http://rocwiki.org/Bill_Gray%27s", "name": "Bill Gray's"}, {"town": "Henrietta", "url": "http://rocwiki.org/Full_Belly_Deli", "name": "Full Belly Deli"}, {"town": "Henrietta", "url": "http://rocwiki.org/Tully%27s", "name": "Tully's"}, {"town": "Henrietta", "url": "http://rocwiki.org/Burger_King", "name": "Burger King"}, {"town": "Henrietta", "url": "http://rocwiki.org/CiCi%27s_Pizza", "name": "CiCi's Pizza"}, {"town": "Henrietta", "url": "http://rocwiki.org/Dairy_Queen", "name": "Dairy Queen"}, {"town": "Henrietta", "url": "http://rocwiki.org/Five_Guys_Burgers_and_Fries", "name": "Five Guys Burgers and Fries"}, {"town": "Henrietta", "url": "http://rocwiki.org/Grand_Super_Buffet", "name": "Grand Super Buffet"}, {"town": "Henrietta", "url": "http://rocwiki.org/Joe%27s_Brooklyn_Pizza", "name": "Joe's Brooklyn Pizza"}, {"town": "Henrietta", "url": "http://rocwiki.org/Moe%27s_Southwest_Grill", "name": "Moe's Southwest Grill"}, {"town": "Henrietta", "url": "http://rocwiki.org/The_Pita_Pit", "name": "The Pita Pit"}, {"town": "Henrietta", "url": "http://rocwiki.org/Subway_Restaurants", "name": "Subway Restaurants"}, {"town": "Henrietta", "url": "http://rocwiki.org/Calios", "name": "Calios"}, {"town": "Henrietta", "url": "http://rocwiki.org/China_Buffet", "name": "China Buffet"}, {"town": "Henrietta", "url": "http://rocwiki.org/International_Food_Market", "name": "International Food Market"}, {"town": "Henrietta", "url": "http://rocwiki.org/Subway_Restaurants", "name": "Subway Restaurants"}, {"town": "Henrietta", "url": "http://rocwiki.org/Tandoor_of_India", "name": "Tandoor of India"}, {"town": "Henrietta", "url": "http://rocwiki.org/Buffalo_Wild_Wings_Grill_%26_Bar", "name": "Buffalo Wild Wings Grill & Bar"}, {"town": "Henrietta", "url": "http://rocwiki.org/Chipotle_Mexican_Grill", "name": "Chipotle Mexican Grill"}, {"town": "Henrietta", "url": "http://rocwiki.org/DiBella%27s", "name": "Dibella's"}, {"town": "Henrietta", "url": "http://rocwiki.org/Great_Northern_Pizza_Kitchens", "name": "Great Northern Pizza Kitchens"}, {"town": "Henrietta", "url": "http://rocwiki.org/LongHorn_Steakhouse", "name": "Longhorn Steakhouse"}, {"town": "Henrietta", "url": "http://rocwiki.org/Red_Robin", "name": "Red Robin"}, {"town": "Henrietta", "url": "http://rocwiki.org/Romano%27s_Macaroni_Grill", "name": "Romano's Macaroni Grill"}, {"town": "Henrietta", "url": "http://rocwiki.org/Aladdin%27s_Natural_Eatery", "name": "Aladdin's Natural Eatery"}, {"town": "Henrietta", "url": "http://rocwiki.org/Lovin%27_Cup", "name": "lovin' cup"}, {"town": "Henrietta", "url": "http://rocwiki.org/Paradiso_Pizza", "name": "Paradiso Pizza"}, {"town": "Henrietta", "url": "http://rocwiki.org/Wok_With_You", "name": "Wok With You"}, {"town": "Henrietta", "url": "http://rocwiki.org/Bruegger%27s", "name": "Bruegger's"}, {"town": "Henrietta", "url": "http://rocwiki.org/Hibachi_Sushi_Buffet", "name": "Hibachi Sushi Buffet"}, {"town": "Henrietta", "url": "http://rocwiki.org/Jitters_Cafe", "name": "Jitters Cafe"}, {"town": "Henrietta", "url": "http://rocwiki.org/Bob%27s_Diner", "name": "Bob's Diner"}, {"town": "Henrietta", "url": "http://rocwiki.org/JB_Quimby%27s_Public_House", "name": "JB Quimby's Public House"}, {"town": "Henrietta", "url": "http://rocwiki.org/Thali_of_India", "name": "Thali of India"}, {"town": "Honeoye Falls", "url": "http://rocwiki.org/Critics_Family_Restaurant", "name": "Critics Family Restaurant"}, {"town": "Honeoye Falls", "url": "http://rocwiki.org/Enjoy_Cafe", "name": "Enjoy Cafe"}, {"town": "Honeoye Falls", "url": "http://rocwiki.org/Flaherty%27s_Three_Flags", "name": "Flaherty's Three Flags"}, {"town": "Honeoye Falls", "url": "http://rocwiki.org/Guida%27s_Pizzeria", "name": "Guida's Pizzeria"}, {"town": "Honeoye Falls", "url": "http://rocwiki.org/The_Brewery_Pub_%26_Grill", "name": "The Brewery Pub & Grill"}, {"town": "Honeoye Falls", "url": "http://rocwiki.org/The_Rabbit_Room", "name": "The Rabbit Room"}, {"town": "Irondequoit", "url": "http://rocwiki.org/2_Ton_Tony%27s", "name": "2 Ton Tony's"}, {"town": "Irondequoit", "url": "http://rocwiki.org/Amico_Pizza", "name": "Amico Pizza"}, {"town": "Irondequoit", "url": "http://rocwiki.org/Atlas_Eats", "name": "Atlas Eats"}, {"town": "Irondequoit", "url": "http://rocwiki.org/Bay_Front_Restaurant", "name": "Bay Front Restaurant"}, {"town": "Irondequoit", "url": "http://rocwiki.org/Carpani%27s", "name": "Carpani's"}, {"town": "Irondequoit", "url": "http://rocwiki.org/East_Ridge_Diner_%26_Steakhouse", "name": "East Ridge Diner & Steakhouse"}, {"town": "Irondequoit", "url": "http://rocwiki.org/East_Ridge_Family_Restaurant", "name": "East Ridge Family Restaurant"}, {"town": "Irondequoit", "url": "http://rocwiki.org/Gigi%27s_Italian_Kitchen_%26_Catering", "name": "Gigi's Italian Kitchen & Catering"}, {"town": "Irondequoit", "url": "http://rocwiki.org/Grand_Super_Buffet", "name": "Grand Super Buffet"}, {"town": "Irondequoit", "url": "http://rocwiki.org/Gourmet_House", "name": "Gourmet House"}, {"town": "Irondequoit", "url": "http://rocwiki.org/Guido%27s_Pasta_Villa", "name": "Guido's Pasta Villa"}, {"town": "Irondequoit", "url": "http://rocwiki.org/IHOP", "name": "IHOP"}, {"town": "Irondequoit", "url": "http://rocwiki.org/Italian_Osteria", "name": "Italian Osteria"}, {"town": "Irondequoit", "url": "http://rocwiki.org/Kai_Jades_Chinese_Restaurant", "name": "Kai Jades Chinese Restaurant"}, {"town": "Irondequoit", "url": "http://rocwiki.org/Keenan%27s_Restaurant", "name": "Keenan's Restaurant"}, {"town": "Irondequoit", "url": "http://rocwiki.org/Kithno%27s_Seafood", "name": "Kithno's Seafood"}, {"town": "Irondequoit", "url": "http://rocwiki.org/Marvin_Mozzeroni%27s", "name": "Marvin Mozzeroni's"}, {"town": "Irondequoit", "url": "http://rocwiki.org/McNeill%27s_Public_House", "name": "McNeill's Public House"}, {"town": "Irondequoit", "url": "http://rocwiki.org/Monte_Alban_Mexican_Grill", "name": "Monte Alban Mexican Grill"}, {"town": "Irondequoit", "url": "http://rocwiki.org/Nick%27s_Sea_Breeze_Inn", "name": "Nick's Sea Breeze Inn"}, {"town": "Irondequoit", "url": "http://rocwiki.org/Olive_Garden", "name": "Olive Garden"}, {"town": "Irondequoit", "url": "http://rocwiki.org/Parkside_Diner", "name": "Parkside Diner"}, {"town": "Irondequoit", "url": "http://rocwiki.org/Rick%27s_Place", "name": "Rick's Place"}, {"town": "Irondequoit", "url": "http://rocwiki.org/Ridgeview_Family_Restaurant", "name": "Ridgeview Family Restaurant"}, {"town": "Irondequoit", "url": "http://rocwiki.org/Sam%27s_Diner", "name": "Sam's Diner"}, {"town": "Irondequoit", "url": "http://rocwiki.org/Schallers", "name": "Schallers"}, {"town": "Irondequoit", "url": "http://rocwiki.org/Shogun_Palace", "name": "Shogun Palace"}, {"town": "Irondequoit", "url": "http://rocwiki.org/Subway_Restaurants", "name": "Subway Restaurants"}, {"town": "Irondequoit", "url": "http://rocwiki.org/Summerville_Grill", "name": "Summerville Grill"}, {"town": "Irondequoit", "url": "http://rocwiki.org/Taste_of_China", "name": "Taste of China"}, {"town": "Irondequoit", "url": "http://rocwiki.org/Uncle_Danny%27s_Family_Restaurant", "name": "Uncle Danny's Family Restaurant"}, {"town": "Irondequoit", "url": "http://rocwiki.org/Vic_and_Irv%27s", "name": "Vic and Irv's"}, {"town": "Irondequoit", "url": "http://rocwiki.org/Viet-Thai_Restaurant", "name": "Viet-Thai Restaurant"}, {"town": "Lima", "url": "http://rocwiki.org/American_Hotel", "name": "American Hotel"}, {"town": "Macedon", "url": "http://rocwiki.org/Flaherty%27s_Three_Flags", "name": "Flaherty's Three Flags"}, {"town": "Penfield", "url": "http://rocwiki.org/All_Star_Pizza", "name": "All Star Pizza"}, {"town": "Penfield", "url": "http://rocwiki.org/Angus_House_%26_Lounge", "name": "Angus House & Lounge"}, {"town": "Penfield", "url": "http://rocwiki.org/Bazil", "name": "Bazil"}, {"town": "Penfield", "url": "http://rocwiki.org/The_Beale", "name": "The Beale"}, {"town": "Penfield", "url": "http://rocwiki.org/Billy%27s_Homestead", "name": "Billy's Homestead"}, {"town": "Penfield", "url": "http://rocwiki.org/Browncroft_Family_Restaurant", "name": "Browncroft Family Restaurant"}, {"town": "Penfield", "url": "http://rocwiki.org/Charley_Brown%27s_Restaurant", "name": "Charley Brown's Restaurant"}, {"town": "Penfield", "url": "http://rocwiki.org/The_Clark_House", "name": "The Clark House"}, {"town": "Penfield", "url": "http://rocwiki.org/Cornerstone_Restaurant_%26_Cafe", "name": "Cornerstone Restaurant & Cafe"}, {"town": "Penfield", "url": "http://rocwiki.org/Dragon_House", "name": "Dragon House"}, {"town": "Penfield", "url": "http://rocwiki.org/Empire_Pizza", "name": "Empire Pizza"}, {"town": "Penfield", "url": "http://rocwiki.org/The_Grill_and_Tap_Room_at_Shadow_Lake", "name": "The Grill and Tap Room at Shadow Lake"}, {"town": "Penfield", "url": "http://rocwiki.org/Hong_Wah_Chinese_Restaurant", "name": "Hong Wah Chinese Restaurant"}, {"town": "Penfield", "url": "http://rocwiki.org/Itacate", "name": "Itacate"}, {"town": "Penfield", "url": "http://rocwiki.org/Joey%27s_Pasta_House", "name": "Joey's Pasta House"}, {"town": "Penfield", "url": "http://rocwiki.org/La_Bella_Vita", "name": "La Bella Vita"}, {"town": "Penfield", "url": "http://rocwiki.org/Lasalle_Steak_%26_Crab", "name": "Lasalle Steak & Crab"}, {"town": "Penfield", "url": "http://rocwiki.org/Lilian%27s_Restaurant_%26_Party_House", "name": "Lilian's Restaurant & Party House"}, {"town": "Penfield", "url": "http://rocwiki.org/Lindburgers", "name": "Lindburgers"}, {"town": "Penfield", "url": "http://rocwiki.org/Michael%27s_Valley_Grill", "name": "Michael's Valley Grill"}, {"town": "Penfield", "url": "http://rocwiki.org/Monte_Alban_Mexican_Grill", "name": "Monte Alban Mexican Grill"}, {"town": "Penfield", "url": "http://rocwiki.org/Monty%27s_Cafe", "name": "Monty's Cafe"}, {"town": "Penfield", "url": "http://rocwiki.org/The_Original_Steves_Diner", "name": "The Original Steves Diner"}, {"town": "Penfield", "url": "http://rocwiki.org/Pattaya_Thai", "name": "Pattaya Thai"}, {"town": "Penfield", "url": "http://rocwiki.org/Rosey%27s_Italian_Cafe", "name": "Rosey's Italian Cafe"}, {"town": "Penfield", "url": "http://rocwiki.org/Royal_Dynasty", "name": "Royal Dynasty"}, {"town": "Penfield", "url": "http://rocwiki.org/Salvatore%27s_Old_Fashioned_Pizzeria", "name": "Salvatore's Old Fashioned Pizzeria"}, {"town": "Penfield", "url": "http://rocwiki.org/Sanibel_Cottage", "name": "Sanibel Cottage"}, {"town": "Penfield", "url": "http://rocwiki.org/Signatures_at_the_Humphrey_House", "name": "Signatures at the Humphrey House"}, {"town": "Penfield", "url": "http://rocwiki.org/Sonny%27s_Deli", "name": "Sonny's Deli"}, {"town": "Penfield", "url": "http://rocwiki.org/Spring_Garden", "name": "Spring Garden"}, {"town": "Penfield", "url": "http://rocwiki.org/Sully%27s_Family_Pizzeria", "name": "Sully's Family Pizzeria"}, {"town": "Penfield", "url": "http://rocwiki.org/Sushi_King", "name": "Sushi King"}, {"town": "Penfield", "url": "http://rocwiki.org/Taco_Bell", "name": "Taco Bell"}, {"town": "Penfield", "url": "http://rocwiki.org/Tandoor_Flame", "name": "Tandoor Flame"}, {"town": "Penfield", "url": "http://rocwiki.org/T-Bones_Steakhouse", "name": "T-Bones Steakhouse"}, {"town": "Penfield", "url": "http://rocwiki.org/Beale_Street_Cafe", "name": "Beale Street Cafe"}, {"town": "Penfield", "url": "http://rocwiki.org/Chili%27s", "name": "Chili's"}, {"town": "Penfield", "url": "http://rocwiki.org/DiBella%27s", "name": "DiBella's"}, {"town": "Penfield", "url": "http://rocwiki.org/Flaherty%27s_Three_Flags", "name": "Flaherty's Three Flags"}, {"town": "Penfield", "url": "http://rocwiki.org/McDonald%27s", "name": "McDonald's"}, {"town": "Penfield", "url": "http://rocwiki.org/Pizza_Hut", "name": "Pizza Hut"}, {"town": "Penfield", "url": "http://rocwiki.org/Phuket_Thai", "name": "Phuket Thai"}, {"town": "Penfield", "url": "http://rocwiki.org/Bruegger%27s", "name": "Bruegger's"}, {"town": "Penfield", "url": "http://rocwiki.org/Burger_King", "name": "Burger King"}, {"town": "Penfield", "url": "http://rocwiki.org/George%27s_Restaurant", "name": "George's Restaurant"}, {"town": "Penfield", "url": "http://rocwiki.org/Panera_Bread", "name": "Panera Bread"}, {"town": "Pittsford", "url": "http://rocwiki.org/Corner_Bakery_Cafe", "name": "Corner Bakery Cafe"}, {"town": "Pittsford", "url": "http://rocwiki.org/Erie_Grill", "name": "Erie Grill"}, {"town": "Pittsford", "url": "http://rocwiki.org/JoJo", "name": "JoJo"}, {"town": "Pittsford", "url": "http://rocwiki.org/Moe%27s_Southwest_Grill", "name": "Moe's Southwest Grill"}, {"town": "Pittsford", "url": "http://rocwiki.org/Monroe%27s_Restaurant", "name": "Monroe's Restaurant"}, {"town": "Pittsford", "url": "http://rocwiki.org/Next_Door_Bar_%26_Grill", "name": "Next Door Bar & Grill"}, {"town": "Pittsford", "url": "http://rocwiki.org/Pittsford_Pub", "name": "Pittsford Pub"}, {"town": "Pittsford", "url": "http://rocwiki.org/Pomodoro_Grill_and_Wine_Bar", "name": "Pomodoro Grill and Wine Bar"}, {"town": "Pittsford", "url": "http://rocwiki.org/The_Pub_at_Bushnell%27s_Basin", "name": "The Pub at Bushnell's Basin"}, {"town": "Pittsford", "url": "http://rocwiki.org/Label_7", "name": "Label 7"}, {"town": "Pittsford", "url": "http://rocwiki.org/Olive%27s_Greek_Taverna", "name": "Olive's Greek Taverna"}, {"town": "Pittsford", "url": "http://rocwiki.org/Applebee%27s", "name": "Applebee's"}, {"town": "Pittsford", "url": "http://rocwiki.org/Benucci%27s", "name": "Benucci's"}, {"town": "Pittsford", "url": "http://rocwiki.org/Black_and_Blue", "name": "Black and Blue"}, {"town": "Pittsford", "url": "http://rocwiki.org/Cheesecake_Factory", "name": "Cheesecake Factory"}, {"town": "Pittsford", "url": "http://rocwiki.org/Chipotle_Mexican_Grill", "name": "Chipotle Mexican Grill"}, {"town": "Pittsford", "url": "http://rocwiki.org/Colie%27s_Cafe", "name": "Colie's Cafe"}, {"town": "Pittsford", "url": "http://rocwiki.org/Five_Guys_Burgers_and_Fries", "name": "Five Guys Burgers and Fries"}, {"town": "Pittsford", "url": "http://rocwiki.org/The_Food_Bar_at_Wegmans", "name": "The Food Bar at Wegmans"}, {"town": "Pittsford", "url": "http://rocwiki.org/Plum_Garden", "name": "Plum Garden"}, {"town": "Pittsford", "url": "http://rocwiki.org/Hicks_and_McCarthy", "name": "Hicks and McCarthy"}, {"town": "Pittsford", "url": "http://rocwiki.org/Aladdin%27s_Natural_Eatery", "name": "Aladdin's Natural Eatery"}, {"town": "Pittsford", "url": "http://rocwiki.org/Simply_Crepes", "name": "Simply Crepes"}, {"town": "Pittsford", "url": "http://rocwiki.org/Village_Coal_Tower", "name": "Village Coal Tower"}, {"town": "Scottsville", "url": "http://rocwiki.org/Amy_Rose_Pizza", "name": "Amy Rose Pizza"}, {"town": "Scottsville", "url": "http://rocwiki.org/China_Panda", "name": "China Panda"}, {"town": "Scottsville", "url": "http://rocwiki.org/Mark%27s_Pizzeria", "name": "Mark's Pizzeria"}, {"town": "Scottsville", "url": "http://rocwiki.org/Scottsville_Diner", "name": "Scottsville Diner"}, {"town": "Spencerport", "url": "http://rocwiki.org/2_Ton_Tony%27s", "name": "2 Ton Tony's"}, {"town": "Spencerport", "url": "http://rocwiki.org/Abe%27s", "name": "Abe's"}, {"town": "Spencerport", "url": "http://rocwiki.org/Chef_King", "name": "Chef King"}, {"town": "Spencerport", "url": "http://rocwiki.org/Cordello%27s", "name": "Cordello's"}, {"town": "Spencerport", "url": "http://rocwiki.org/Galley_Restaurant", "name": "Galley Restaurant"}, {"town": "Spencerport", "url": "http://rocwiki.org/Grandpa_Sam%27s", "name": "Grandpa Sam's"}, {"town": "Spencerport", "url": "http://rocwiki.org/Little_Louie%27s_Pizzeria", "name": "Little Louie's Pizzeria"}, {"town": "Spencerport", "url": "http://rocwiki.org/Mangia_Mangia", "name": "Mangia Mangia"}, {"town": "Spencerport", "url": "http://rocwiki.org/Pizza_Shack_1", "name": "Pizza Shack 1"}, {"town": "Spencerport", "url": "http://rocwiki.org/Taste_of_Texas_Bar-B-Q", "name": "Taste of Texas Bar-B-Q"}, {"town": "Spencerport", "url": "http://rocwiki.org/Krony%27s_Pizza", "name": "Krony's Pizza"}, {"town": "Spencerport", "url": "http://rocwiki.org/Pineview_Family_Restaurant", "name": "Pineview Family Restaurant"}, {"town": "Victor", "url": "http://rocwiki.org/Bernardo%27s_Pizza_%26_Submarines", "name": "Bernardo's Pizza & Submarines"}, {"town": "Victor", "url": "http://rocwiki.org/Bistro_11", "name": "Bistro 11"}, {"town": "Victor", "url": "http://rocwiki.org/Burger_Shack_Grill", "name": "Burger Shack Grill"}, {"town": "Victor", "url": "http://rocwiki.org/Chili%27s", "name": "Chili's"}, {"town": "Victor", "url": "http://rocwiki.org/Cole_%26_Parks", "name": "Cole & Parks"}, {"town": "Victor", "url": "http://rocwiki.org/Denny%27s", "name": "Denny's"}, {"town": "Victor", "url": "http://rocwiki.org/Dunkin%27_Donuts", "name": "Dunkin' Donuts"}, {"town": "Victor", "url": "http://rocwiki.org/Food_at_Fisher%27s_Station", "name": "Food at Fisher's Station"}, {"town": "Victor", "url": "http://rocwiki.org/Giovanni%27s_Ristorante", "name": "Giovanni's Ristorante"}, {"town": "Victor", "url": "http://rocwiki.org/India_House", "name": "India House"}, {"town": "Victor", "url": "http://rocwiki.org/LongHorn_Steakhouse", "name": "Longhorn Steakhouse"}, {"town": "Victor", "url": "http://rocwiki.org/Lucca_Wood_Fired_Pizza", "name": "Lucca Wood Fired Pizza"}, {"town": "Victor", "url": "http://rocwiki.org/Mickey_Finn%27s_Station_One", "name": "Mickey Finn's Station One"}, {"town": "Victor", "url": "http://rocwiki.org/Olive_Garden", "name": "Olive Garden"}, {"town": "Victor", "url": "http://rocwiki.org/Otto_Tomotto%27s", "name": "Otto Tomotto's"}, {"town": "Victor", "url": "http://rocwiki.org/Panda_Restaurant", "name": "Panda Restaurant"}, {"town": "Victor", "url": "http://rocwiki.org/Papa_Jack%27s_Grill", "name": "Papa Jack's Grill"}, {"town": "Victor", "url": "http://rocwiki.org/Pontillo%27s", "name": "Pontillo's"}, {"town": "Victor", "url": "http://rocwiki.org/Posella%27s_Pizzeria", "name": "Posella's Pizzeria"}, {"town": "Victor", "url": "http://rocwiki.org/salvatore%27s", "name": "Salvatore's"}, {"town": "Victor", "url": "http://rocwiki.org/TGI_Friday%27s", "name": "TGI Friday's"}, {"town": "Victor", "url": "http://rocwiki.org/The_Distillery", "name": "The Distillery"}, {"town": "Victor", "url": "http://rocwiki.org/The_Soup_Spoon", "name": "The Soup Spoon"}, {"town": "Victor", "url": "http://rocwiki.org/The_Thirsty_Turtle", "name": "The Thirsty Turtle"}, {"town": "Victor", "url": "http://rocwiki.org/Tim_Hortons", "name": "Tim Hortons"}, {"town": "Victor", "url": "http://rocwiki.org/Uno_Chicago_Grill", "name": "Uno Chicago Grill"}, {"town": "Victor", "url": "http://rocwiki.org/Victor_Village_Inn", "name": "Victor Village Inn"}, {"town": "Victor", "url": "http://rocwiki.org/Wendy%27s", "name": "Wendy's"}, {"town": "Victor", "url": "http://rocwiki.org/Allen%27s_Cobblestone_Deli", "name": "Allen's Cobblestone Deli"}, {"town": "Victor", "url": "http://rocwiki.org/Amiel%27s", "name": "Amiel's"}, {"town": "Victor", "url": "http://rocwiki.org/Little_Caesars_Pizza", "name": "Little Caesars Pizza"}, {"town": "Victor", "url": "http://rocwiki.org/Moe%27s_Southwest_Grill", "name": "Moe's Southwest Grill"}, {"town": "Victor", "url": "http://rocwiki.org/Rainbow_Wok", "name": "Rainbow Wok"}, {"town": "Victor", "url": "http://rocwiki.org/UMI_Japanese_Steakhouse_%26_Sushi_Bar", "name": "UMI Japanese Steakhouse & Sushi Bar"}, {"town": "Victor", "url": "http://rocwiki.org/Arby%27s", "name": "Arby's"}, {"town": "Victor", "url": "http://rocwiki.org/Auntie_Anne%27s", "name": "Auntie Anne's"}, {"town": "Victor", "url": "http://rocwiki.org/Biaggi%27s", "name": "Biaggi's"}, {"town": "Victor", "url": "http://rocwiki.org/Bonefish_Grill", "name": "Bonefish Grill"}, {"town": "Victor", "url": "http://rocwiki.org/Burger_King", "name": "Burger King"}, {"town": "Victor", "url": "http://rocwiki.org/Champps", "name": "Champps"}, {"town": "Victor", "url": "http://rocwiki.org/Charley%27s_Grilled_Subs", "name": "Charley's Grilled Subs"}, {"town": "Victor", "url": "http://rocwiki.org/Colie%27s_Cafe", "name": "Colie's Cafe"}, {"town": "Victor", "url": "http://rocwiki.org/Friendly%27s", "name": "Friendly's"}, {"town": "Victor", "url": "http://rocwiki.org/P.F._Chang%27s_China_Bistro", "name": "P.F. Chang's China Bistro"}, {"town": "Victor", "url": "http://rocwiki.org/Sbarro", "name": "Sbarro"}, {"town": "Victor", "url": "http://rocwiki.org/Subway_Restaurants", "name": "Subway Restaurants"}, {"town": "Victor", "url": "http://rocwiki.org/Taco_Bell", "name": "Taco Bell"}, {"town": "Victor", "url": "http://rocwiki.org/Tom_Wahl%27s", "name": "Tom Wahl's"}, {"town": "Webster", "url": "http://rocwiki.org/Atlantic_Family_Restaurant", "name": "Atlantic Family Restaurant"}, {"town": "Webster", "url": "http://rocwiki.org/Bruster%27s", "name": "Bruster's"}, {"town": "Webster", "url": "http://rocwiki.org/Castaways_On_the_Lake", "name": "Castaways On the Lake"}, {"town": "Webster", "url": "http://rocwiki.org/The_Garlic_Pit", "name": "The Garlic Pit"}, {"town": "Webster", "url": "http://rocwiki.org/Gyromania", "name": "Gyromania"}, {"town": "Webster", "url": "http://rocwiki.org/Hedges_9_Mile_Point_Restaurant", "name": "Hedges 9 Mile Point Restaurant"}, {"town": "Webster", "url": "http://rocwiki.org/Jade_Palace", "name": "Jade Palace"}, {"town": "Webster", "url": "http://rocwiki.org/Jasmine%27s_Asian_Fusion", "name": "Jasmine's Asian Fusion"}, {"town": "Webster", "url": "http://rocwiki.org/Jimmy_John%27s_Gourmet_Sandwiches", "name": "Jimmy John's Gourmet Sandwiches"}, {"town": "Webster", "url": "http://rocwiki.org/Mama_Lor%27s_Cafe", "name": "Mama Lor's Cafe"}, {"town": "Webster", "url": "http://rocwiki.org/Martino%27s_Pizzeria", "name": "Martino's Pizzeria"}, {"town": "Webster", "url": "http://rocwiki.org/Monte_Alban_Mexican_Grill", "name": "Monte Alban Mexican Grill"}, {"town": "Webster", "url": "http://rocwiki.org/Nutcracker_Family_Restaurant", "name": "Nutcracker Family Restaurant"}, {"town": "Webster", "url": "http://rocwiki.org/Papa_John%27s", "name": "Papa John's"}, {"town": "Webster", "url": "http://rocwiki.org/Phuket_Thai", "name": "Phuket Thai"}, {"town": "Webster", "url": "http://rocwiki.org/Rhino%27s_Pizzeria_%26_Deli", "name": "Rhino's Pizzeria & Deli"}, {"town": "Webster", "url": "http://rocwiki.org/Streppa%27s_Bistro", "name": "Streppa's Bistro"}, {"town": "Webster", "url": "http://rocwiki.org/T%27s_Family_Restaurant", "name": "T's Family Restaurant"}, {"town": "Webster", "url": "http://rocwiki.org/Cold_Stone_Creamery", "name": "Cold Stone Creamery"}, {"town": "Webster", "url": "http://rocwiki.org/Moe%27s_Southwest_Grill", "name": "Moe's Southwest Grill"}, {"town": "Webster", "url": "http://rocwiki.org/Panera_Bread", "name": "Panera Bread"}, {"town": "Webster", "url": "http://rocwiki.org/Red_Robin", "name": "Red Robin"}, {"town": "Webster", "url": "http://rocwiki.org/Royal_Dynasty", "name": "Royal Dynasty"}, {"town": "Webster", "url": "http://rocwiki.org/Spring_Garden", "name": "Spring Garden"}, {"town": "Webster", "url": "http://rocwiki.org/Starbucks", "name": "Starbucks"}, {"town": "Webster", "url": "http://rocwiki.org/Uno_Chicago_Grill", "name": "Uno Chicago Grill"}, {"town": "Webster", "url": "http://rocwiki.org/Burger_King", "name": "Burger King"}, {"town": "Webster", "url": "http://rocwiki.org/China_Chef", "name": "China Chef"}, {"town": "Webster", "url": "http://rocwiki.org/Proietti%27s", "name": "Proietti's"}, {"town": "Webster", "url": "http://rocwiki.org/Sogo_Japanese_Steakhouse", "name": "Sogo Japanese Steakhouse"}, {"town": "Webster", "url": "http://rocwiki.org/Starbucks", "name": "Starbucks"}, {"town": "Webster", "url": "http://rocwiki.org/Subway_Restaurants", "name": "Subway Restaurants"}, {"town": "Webster", "url": "http://rocwiki.org/Hooligans_Eastside_Grill", "name": "Hooligans Eastside Grill"}, {"town": "Webster", "url": "http://rocwiki.org/Moma_Ristorante_Italiano", "name": "Moma Ristorante Italiano"}, {"town": "Webster", "url": "http://rocwiki.org/Pontillo%27s", "name": "Pontillo's"}, {"town": "Webster", "url": "http://rocwiki.org/Taka_House_Japanese_Restaurant", "name": "Taka House Japanese Restaurant"}, {"town": "Webster", "url": "http://rocwiki.org/Barry%E2%80%99s_Old_School_Irish", "name": "Barry\u2019s Old School Irish"}, {"town": "Webster", "url": "http://rocwiki.org/Coach_Sports_Bar", "name": "Coach Sports Bar"}, {"town": "Webster", "url": "http://rocwiki.org/Dunkin%27_Donuts", "name": "Dunkin' Donuts"}, {"town": "Webster", "url": "http://rocwiki.org/Golden_Boys", "name": "Golden Boys"}, {"town": "Webster", "url": "http://rocwiki.org/Hank%27s_Ice_Cream_%26_Roast_Beef_Sandwiches", "name": "Hank's Ice Cream & Roast Beef Sandwiches"}, {"town": "Webster", "url": "http://rocwiki.org/Hatter%27s_Pub", "name": "Hatter's Pub"}, {"town": "Webster", "url": "http://rocwiki.org/Maa%27s_Diner", "name": "Maa's Diner"}, {"town": "Webster", "url": "http://rocwiki.org/Maria%27s_Mexican_Restaurant", "name": "Maria's Mexican Restaurant"}, {"town": "Webster", "url": "http://rocwiki.org/Mark%27s_Pizzeria", "name": "Mark's Pizzeria"}, {"town": "Webster", "url": "http://rocwiki.org/Marvin_Mozzeroni%27s", "name": "Marvin Mozzeroni's"}, {"town": "Webster", "url": "http://rocwiki.org/McDonald%27s", "name": "McDonald's"}, {"town": "Webster", "url": "http://rocwiki.org/No._1", "name": "No. 1"}, {"town": "Webster", "url": "http://rocwiki.org/Prime_Steakhouse", "name": "Prime Steakhouse"}, {"town": "Webster", "url": "http://rocwiki.org/Rubino%27s", "name": "Rubino's"}, {"town": "Webster", "url": "http://rocwiki.org/Webster_Hots", "name": "Webster Hots"}]